{
"viewingYear": "all",
"totalViewingCount": 1523,
"stats": [
{
"decade": "1920s",
"viewingCount": 12
},
{
"decade": "1930s",
"viewingCount": 191
},
{
"decade": "1940s",
"viewingCount": 105
},
{
"decade": "1950s",
"viewingCount": 109
},
{
"decade": "1960s",
"viewingCount": 102
},
{
"decade": "1970s",
"viewingCount": 167
},
{
"decade": "1980s",
"viewingCount": 240
},
{
"decade": "1990s",
"viewingCount": 80
},
{
"decade": "2000s",
"viewingCount": 124
},
{
"decade": "2010s",
"viewingCount": 341
},
{
"decade": "2020s",
"viewingCount": 52
}
]
}