{
  "year": "2022",
  "newTitleCount": 161,
  "viewingCount": 206,
  "titleCount": 205,
  "mediaDistribution": [
    {
      "name": "Watch TCM",
      "count": 78
    },
    {
      "name": "Blu-ray",
      "count": 42
    },
    {
      "name": "iTunes",
      "count": 24
    },
    {
      "name": "4k UHD Blu-ray",
      "count": 12
    },
    {
      "name": "Criterion Channel",
      "count": 12
    },
    {
      "name": "Arrow Player",
      "count": 9
    },
    {
      "name": "HBO Max",
      "count": 8
    },
    {
      "name": "Netflix",
      "count": 4
    },
    {
      "name": "Amazon",
      "count": 4
    },
    {
      "name": "Disney+",
      "count": 3
    }
  ],
  "decadeDistribution": [
    {
      "name": "1930s",
      "count": 30
    },
    {
      "name": "1940s",
      "count": 34
    },
    {
      "name": "1950s",
      "count": 10
    },
    {
      "name": "1960s",
      "count": 9
    },
    {
      "name": "1970s",
      "count": 24
    },
    {
      "name": "1980s",
      "count": 36
    },
    {
      "name": "1990s",
      "count": 9
    },
    {
      "name": "2000s",
      "count": 20
    },
    {
      "name": "2010s",
      "count": 13
    },
    {
      "name": "2020s",
      "count": 21
    }
  ],
  "mostWatchedTitles": [
    {
      "title": "Event Horizon",
      "imdbId": "tt0119081",
      "year": "1997",
      "count": 2,
      "slug": "event-horizon-1997"
    }
  ],
  "mostWatchedDirectors": [
    {
      "name": "Wes Craven",
      "count": 5,
      "slug": "wes-craven",
      "viewings": [
        {
          "sequence": 1228,
          "date": "2022-01-12",
          "slug": "the-hills-have-eyes-1977",
          "title": "The Hills Have Eyes",
          "medium": "4k UHD Blu-ray",
          "venue": null,
          "year": "1977"
        },
        {
          "sequence": 1230,
          "date": "2022-01-14",
          "slug": "deadly-blessing-1981",
          "title": "Deadly Blessing",
          "medium": "Blu-ray",
          "venue": null,
          "year": "1981"
        },
        {
          "sequence": 1235,
          "date": "2022-01-26",
          "slug": "swamp-thing-1982",
          "title": "Swamp Thing",
          "medium": "Amazon",
          "venue": null,
          "year": "1982"
        },
        {
          "sequence": 1241,
          "date": "2022-02-02",
          "slug": "the-hills-have-eyes-part-ii-1984",
          "title": "The Hills Have Eyes Part II",
          "medium": "Arrow Player",
          "venue": null,
          "year": "1984"
        },
        {
          "sequence": 1247,
          "date": "2022-02-09",
          "slug": "a-nightmare-on-elm-street-1984",
          "title": "A Nightmare on Elm Street",
          "medium": "Blu-ray",
          "venue": null,
          "year": "1984"
        }
      ]
    },
    {
      "name": "John Ford",
      "count": 5,
      "slug": "john-ford",
      "viewings": [
        {
          "sequence": 1292,
          "date": "2022-06-21",
          "slug": "pilgrimage-1933",
          "title": "Pilgrimage",
          "medium": "Criterion Channel",
          "venue": null,
          "year": "1933"
        },
        {
          "sequence": 1293,
          "date": "2022-06-22",
          "slug": "steamboat-round-the-bend-1935",
          "title": "Steamboat Round the Bend",
          "medium": "Criterion Channel",
          "venue": null,
          "year": "1935"
        },
        {
          "sequence": 1294,
          "date": "2022-06-27",
          "slug": "the-plough-and-the-stars-1936",
          "title": "The Plough and the Stars",
          "medium": "Criterion Channel",
          "venue": null,
          "year": "1936"
        },
        {
          "sequence": 1295,
          "date": "2022-06-29",
          "slug": "doctor-bull-1933",
          "title": "Doctor Bull",
          "medium": "Criterion Channel",
          "venue": null,
          "year": "1933"
        },
        {
          "sequence": 1308,
          "date": "2022-07-29",
          "slug": "the-brat-1931",
          "title": "The Brat",
          "medium": "OK.ru",
          "venue": null,
          "year": "1931"
        }
      ]
    },
    {
      "name": "Raoul Walsh",
      "count": 5,
      "slug": null,
      "viewings": [
        {
          "sequence": 1349,
          "date": "2022-09-13",
          "slug": "high-sierra-1941",
          "title": "High Sierra",
          "medium": "Watch TCM",
          "venue": null,
          "year": "1940"
        },
        {
          "sequence": 1372,
          "date": "2022-10-04",
          "slug": "they-drive-by-night-1940",
          "title": "They Drive by Night",
          "medium": "Watch TCM",
          "venue": null,
          "year": "1940"
        },
        {
          "sequence": 1378,
          "date": "2022-10-12",
          "slug": null,
          "title": "The Roaring Twenties",
          "medium": "Watch TCM",
          "venue": null,
          "year": "1939"
        },
        {
          "sequence": 1401,
          "date": "2022-10-26",
          "slug": null,
          "title": "Desperate Journey",
          "medium": "Watch TCM",
          "venue": null,
          "year": "1942"
        },
        {
          "sequence": 1407,
          "date": "2022-10-28",
          "slug": null,
          "title": "Uncertain Glory",
          "medium": "Watch TCM",
          "venue": null,
          "year": "1944"
        }
      ]
    },
    {
      "name": "Lewis Seiler",
      "count": 4,
      "slug": null,
      "viewings": [
        {
          "sequence": 1344,
          "date": "2022-09-09",
          "slug": "king-of-the-underworld-1939",
          "title": "King of the Underworld",
          "medium": "Watch TCM",
          "venue": null,
          "year": "1939"
        },
        {
          "sequence": 1347,
          "date": "2022-09-11",
          "slug": "the-big-shot-1942",
          "title": "The Big Shot",
          "medium": "Watch TCM",
          "venue": null,
          "year": "1942"
        },
        {
          "sequence": 1376,
          "date": "2022-10-06",
          "slug": null,
          "title": "It All Came True",
          "medium": "Watch TCM",
          "venue": null,
          "year": "1940"
        },
        {
          "sequence": 1380,
          "date": "2022-10-14",
          "slug": null,
          "title": "Crime School",
          "medium": "Watch TCM",
          "venue": null,
          "year": "1938"
        }
      ]
    },
    {
      "name": "Rob Zombie",
      "count": 3,
      "slug": null,
      "viewings": [
        {
          "sequence": 1231,
          "date": "2022-01-17",
          "slug": "3-from-hell-2019",
          "title": "3 from Hell",
          "medium": "iTunes",
          "venue": null,
          "year": "2019"
        },
        {
          "sequence": 1267,
          "date": "2022-03-31",
          "slug": "halloween-2007",
          "title": "Halloween",
          "medium": "iTunes",
          "venue": null,
          "year": "2007"
        },
        {
          "sequence": 1268,
          "date": "2022-03-31",
          "slug": "halloween-ii-2009",
          "title": "Halloween II",
          "medium": "iTunes",
          "venue": null,
          "year": "2009"
        }
      ]
    },
    {
      "name": "Brian De Palma",
      "count": 3,
      "slug": "brian-de-palma",
      "viewings": [
        {
          "sequence": 1239,
          "date": "2022-01-31",
          "slug": "blow-out-1981",
          "title": "Blow Out",
          "medium": "Blu-ray",
          "venue": null,
          "year": "1981"
        },
        {
          "sequence": 1250,
          "date": "2022-02-12",
          "slug": "scarface-1983",
          "title": "Scarface",
          "medium": "4k UHD Blu-ray",
          "venue": null,
          "year": "1983"
        },
        {
          "sequence": 1269,
          "date": "2022-04-04",
          "slug": "body-double-1984",
          "title": "Body Double",
          "medium": "Blu-ray",
          "venue": null,
          "year": "1984"
        }
      ]
    },
    {
      "name": "Darren Lynn Bousman",
      "count": 3,
      "slug": null,
      "viewings": [
        {
          "sequence": 1305,
          "date": "2022-07-22",
          "slug": "saw-ii-2005",
          "title": "Saw II",
          "medium": "Blu-ray",
          "venue": null,
          "year": "2005"
        },
        {
          "sequence": 1307,
          "date": "2022-07-28",
          "slug": "saw-iii-2006",
          "title": "Saw III",
          "medium": "Blu-ray",
          "venue": null,
          "year": "2006"
        },
        {
          "sequence": 1315,
          "date": "2022-08-10",
          "slug": "saw-iv-2007",
          "title": "Saw IV",
          "medium": "Blu-ray",
          "venue": null,
          "year": "2007"
        }
      ]
    },
    {
      "name": "Lloyd Bacon",
      "count": 3,
      "slug": null,
      "viewings": [
        {
          "sequence": 1341,
          "date": "2022-09-07",
          "slug": "invisible-stripes-1939",
          "title": "Invisible Stripes",
          "medium": "Watch TCM",
          "venue": null,
          "year": "1939"
        },
        {
          "sequence": 1375,
          "date": "2022-10-06",
          "slug": "the-oklahoma-kid-1939",
          "title": "The Oklahoma Kid",
          "medium": "Watch TCM",
          "venue": null,
          "year": "1939"
        },
        {
          "sequence": 1379,
          "date": "2022-10-13",
          "slug": null,
          "title": "Racket Busters",
          "medium": "Watch TCM",
          "venue": null,
          "year": "1938"
        }
      ]
    },
    {
      "name": "Julia Ducournau",
      "count": 2,
      "slug": null,
      "viewings": [
        {
          "sequence": 1226,
          "date": "2022-01-09",
          "slug": "raw-2016",
          "title": "Raw",
          "medium": "Netflix",
          "venue": null,
          "year": "2016"
        },
        {
          "sequence": 1232,
          "date": "2022-01-20",
          "slug": "titane-2021",
          "title": "Titane",
          "medium": "iTunes",
          "venue": null,
          "year": "2021"
        }
      ]
    },
    {
      "name": "Paul W.S. Anderson",
      "count": 2,
      "slug": null,
      "viewings": [
        {
          "sequence": 1236,
          "date": "2022-01-28",
          "slug": "event-horizon-1997",
          "title": "Event Horizon",
          "medium": "HBO Max",
          "venue": null,
          "year": "1997"
        },
        {
          "sequence": 1277,
          "date": "2022-05-29",
          "slug": "event-horizon-1997",
          "title": "Event Horizon",
          "medium": "35mm",
          "venue": "Prince Charles Cinema",
          "year": "1997"
        }
      ]
    }
  ],
  "mostWatchedPerformers": [
    {
      "name": "Humphrey Bogart",
      "count": 19,
      "slug": "humphrey-bogart",
      "viewings": [
        {
          "sequence": 1324,
          "date": "2022-08-20",
          "slug": "virginia-city-1940",
          "title": "Virginia City",
          "medium": "Watch TCM",
          "venue": null,
          "year": "1940"
        },
        {
          "sequence": 1341,
          "date": "2022-09-07",
          "slug": "invisible-stripes-1939",
          "title": "Invisible Stripes",
          "medium": "Watch TCM",
          "venue": null,
          "year": "1939"
        },
        {
          "sequence": 1344,
          "date": "2022-09-09",
          "slug": "king-of-the-underworld-1939",
          "title": "King of the Underworld",
          "medium": "Watch TCM",
          "venue": null,
          "year": "1939"
        },
        {
          "sequence": 1347,
          "date": "2022-09-11",
          "slug": "the-big-shot-1942",
          "title": "The Big Shot",
          "medium": "Watch TCM",
          "venue": null,
          "year": "1942"
        },
        {
          "sequence": 1349,
          "date": "2022-09-13",
          "slug": "high-sierra-1941",
          "title": "High Sierra",
          "medium": "Watch TCM",
          "venue": null,
          "year": "1940"
        },
        {
          "sequence": 1350,
          "date": "2022-09-14",
          "slug": "dead-reckoning-1947",
          "title": "Dead Reckoning",
          "medium": "Watch TCM",
          "venue": null,
          "year": "1946"
        },
        {
          "sequence": 1361,
          "date": "2022-09-24",
          "slug": "chain-lightning-1950",
          "title": "Chain Lightning",
          "medium": "Watch TCM",
          "venue": null,
          "year": "1950"
        },
        {
          "sequence": 1362,
          "date": "2022-09-24",
          "slug": "men-are-such-fools-1938",
          "title": "Men Are Such Fools",
          "medium": "Watch TCM",
          "venue": null,
          "year": "1938"
        },
        {
          "sequence": 1368,
          "date": "2022-09-30",
          "slug": "three-on-a-match-1932",
          "title": "Three on a Match",
          "medium": "Watch TCM",
          "venue": null,
          "year": "1932"
        },
        {
          "sequence": 1369,
          "date": "2022-10-01",
          "slug": "china-clipper-1936",
          "title": "China Clipper",
          "medium": "Watch TCM",
          "venue": null,
          "year": "1936"
        },
        {
          "sequence": 1370,
          "date": "2022-10-03",
          "slug": "swing-your-lady-1938",
          "title": "Swing Your Lady",
          "medium": "Watch TCM",
          "venue": null,
          "year": "1938"
        },
        {
          "sequence": 1371,
          "date": "2022-10-04",
          "slug": "two-against-the-world-1936",
          "title": "Two Against the World",
          "medium": "Watch TCM",
          "venue": null,
          "year": "1936"
        },
        {
          "sequence": 1372,
          "date": "2022-10-04",
          "slug": "they-drive-by-night-1940",
          "title": "They Drive by Night",
          "medium": "Watch TCM",
          "venue": null,
          "year": "1940"
        },
        {
          "sequence": 1373,
          "date": "2022-10-05",
          "slug": "conflict-1945",
          "title": "Conflict",
          "medium": "Watch TCM",
          "venue": null,
          "year": "1945"
        },
        {
          "sequence": 1375,
          "date": "2022-10-06",
          "slug": "the-oklahoma-kid-1939",
          "title": "The Oklahoma Kid",
          "medium": "Watch TCM",
          "venue": null,
          "year": "1939"
        },
        {
          "sequence": 1376,
          "date": "2022-10-06",
          "slug": null,
          "title": "It All Came True",
          "medium": "Watch TCM",
          "venue": null,
          "year": "1940"
        },
        {
          "sequence": 1378,
          "date": "2022-10-12",
          "slug": null,
          "title": "The Roaring Twenties",
          "medium": "Watch TCM",
          "venue": null,
          "year": "1939"
        },
        {
          "sequence": 1379,
          "date": "2022-10-13",
          "slug": null,
          "title": "Racket Busters",
          "medium": "Watch TCM",
          "venue": null,
          "year": "1938"
        },
        {
          "sequence": 1380,
          "date": "2022-10-14",
          "slug": null,
          "title": "Crime School",
          "medium": "Watch TCM",
          "venue": null,
          "year": "1938"
        }
      ]
    },
    {
      "name": "Tobin Bell",
      "count": 6,
      "slug": null,
      "viewings": [
        {
          "sequence": 1301,
          "date": "2022-07-08",
          "slug": "saw-2004",
          "title": "Saw",
          "medium": "Blu-ray",
          "venue": null,
          "year": "2004"
        },
        {
          "sequence": 1305,
          "date": "2022-07-22",
          "slug": "saw-ii-2005",
          "title": "Saw II",
          "medium": "Blu-ray",
          "venue": null,
          "year": "2005"
        },
        {
          "sequence": 1307,
          "date": "2022-07-28",
          "slug": "saw-iii-2006",
          "title": "Saw III",
          "medium": "Blu-ray",
          "venue": null,
          "year": "2006"
        },
        {
          "sequence": 1315,
          "date": "2022-08-10",
          "slug": "saw-iv-2007",
          "title": "Saw IV",
          "medium": "Blu-ray",
          "venue": null,
          "year": "2007"
        },
        {
          "sequence": 1319,
          "date": "2022-08-12",
          "slug": "saw-v-2008",
          "title": "Saw V",
          "medium": "Blu-ray",
          "venue": null,
          "year": "2008"
        },
        {
          "sequence": 1346,
          "date": "2022-09-10",
          "slug": "saw-vi-2009",
          "title": "Saw VI",
          "medium": "Blu-ray",
          "venue": null,
          "year": "2009"
        }
      ]
    },
    {
      "name": "Bette Davis",
      "count": 6,
      "slug": "bette-davis",
      "viewings": [
        {
          "sequence": 1342,
          "date": "2022-09-07",
          "slug": "the-corn-is-green-1945",
          "title": "The Corn Is Green",
          "medium": "Watch TCM",
          "venue": null,
          "year": "1945"
        },
        {
          "sequence": 1368,
          "date": "2022-09-30",
          "slug": "three-on-a-match-1932",
          "title": "Three on a Match",
          "medium": "Watch TCM",
          "venue": null,
          "year": "1932"
        },
        {
          "sequence": 1377,
          "date": "2022-10-10",
          "slug": null,
          "title": "Now, Voyager",
          "medium": "Watch TCM",
          "venue": null,
          "year": "1942"
        },
        {
          "sequence": 1386,
          "date": "2022-10-18",
          "slug": null,
          "title": "The Bride Came C.O.D.",
          "medium": "Watch TCM",
          "venue": null,
          "year": "1941"
        },
        {
          "sequence": 1390,
          "date": "2022-10-21",
          "slug": null,
          "title": "It's Love I'm After",
          "medium": "Watch TCM",
          "venue": null,
          "year": "1937"
        },
        {
          "sequence": 1418,
          "date": "2022-11-14",
          "slug": null,
          "title": "The Working Man",
          "medium": "Watch TCM",
          "venue": null,
          "year": "1933"
        }
      ]
    },
    {
      "name": "Cary Grant",
      "count": 5,
      "slug": "cary-grant",
      "viewings": [
        {
          "sequence": 1266,
          "date": "2022-03-28",
          "slug": "merrily-we-go-to-hell-1932",
          "title": "Merrily We Go to Hell",
          "medium": "Criterion Channel",
          "venue": null,
          "year": "1932"
        },
        {
          "sequence": 1329,
          "date": "2022-08-26",
          "slug": "topper-1937",
          "title": "Topper",
          "medium": "Watch TCM",
          "venue": null,
          "year": "1937"
        },
        {
          "sequence": 1334,
          "date": "2022-08-31",
          "slug": "penny-serenade-1941",
          "title": "Penny Serenade",
          "medium": "Watch TCM",
          "venue": null,
          "year": "1941"
        },
        {
          "sequence": 1337,
          "date": "2022-09-02",
          "slug": "every-girl-should-be-married-1948",
          "title": "Every Girl Should Be Married",
          "medium": "Watch TCM",
          "venue": null,
          "year": "1948"
        },
        {
          "sequence": 1358,
          "date": "2022-09-20",
          "slug": "suzy-1936",
          "title": "Suzy",
          "medium": "Watch TCM",
          "venue": null,
          "year": "1936"
        }
      ]
    },
    {
      "name": "John Wayne",
      "count": 5,
      "slug": "john-wayne",
      "viewings": [
        {
          "sequence": 1287,
          "date": "2022-06-19",
          "slug": "ride-him-cowboy-1932",
          "title": "Ride Him, Cowboy",
          "medium": "iTunes",
          "venue": null,
          "year": "1932"
        },
        {
          "sequence": 1288,
          "date": "2022-06-19",
          "slug": "haunted-gold-1932",
          "title": "Haunted Gold",
          "medium": "iTunes",
          "venue": null,
          "year": "1932"
        },
        {
          "sequence": 1322,
          "date": "2022-08-18",
          "slug": "the-man-from-monterey-1933",
          "title": "The Man from Monterey",
          "medium": "Watch TCM",
          "venue": null,
          "year": "1933"
        },
        {
          "sequence": 1355,
          "date": "2022-09-18",
          "slug": "reunion-in-france-1942",
          "title": "Reunion in France",
          "medium": "Watch TCM",
          "venue": null,
          "year": "1942"
        },
        {
          "sequence": 1416,
          "date": "2022-11-07",
          "slug": "the-lawless-frontier-1934",
          "title": "The Lawless Frontier",
          "medium": "Watch TCM",
          "venue": null,
          "year": "1934"
        }
      ]
    },
    {
      "name": "William Powell",
      "count": 5,
      "slug": "william-powell",
      "viewings": [
        {
          "sequence": 1289,
          "date": "2022-06-19",
          "slug": "jewel-robbery-1932",
          "title": "Jewel Robbery",
          "medium": "DVD",
          "venue": null,
          "year": "1932"
        },
        {
          "sequence": 1323,
          "date": "2022-08-19",
          "slug": "the-hoodlum-saint-1946",
          "title": "The Hoodlum Saint",
          "medium": "Watch TCM",
          "venue": null,
          "year": "1946"
        },
        {
          "sequence": 1354,
          "date": "2022-09-17",
          "slug": "the-great-ziegfeld-1936",
          "title": "The Great Ziegfeld",
          "medium": "Watch TCM",
          "venue": null,
          "year": "1936"
        },
        {
          "sequence": 1360,
          "date": "2022-09-23",
          "slug": null,
          "title": "Double Wedding",
          "medium": "Watch TCM",
          "venue": null,
          "year": "1937"
        },
        {
          "sequence": 1363,
          "date": "2022-09-26",
          "slug": null,
          "title": "I Love You Again",
          "medium": "Watch TCM",
          "venue": null,
          "year": "1940"
        }
      ]
    },
    {
      "name": "Moroni Olsen",
      "count": 5,
      "slug": null,
      "viewings": [
        {
          "sequence": 1294,
          "date": "2022-06-27",
          "slug": "the-plough-and-the-stars-1936",
          "title": "The Plough and the Stars",
          "medium": "Criterion Channel",
          "venue": null,
          "year": "1936"
        },
        {
          "sequence": 1324,
          "date": "2022-08-20",
          "slug": "virginia-city-1940",
          "title": "Virginia City",
          "medium": "Watch TCM",
          "venue": null,
          "year": "1940"
        },
        {
          "sequence": 1341,
          "date": "2022-09-07",
          "slug": "invisible-stripes-1939",
          "title": "Invisible Stripes",
          "medium": "Watch TCM",
          "venue": null,
          "year": "1939"
        },
        {
          "sequence": 1355,
          "date": "2022-09-18",
          "slug": "reunion-in-france-1942",
          "title": "Reunion in France",
          "medium": "Watch TCM",
          "venue": null,
          "year": "1942"
        },
        {
          "sequence": 1385,
          "date": "2022-10-16",
          "slug": "the-long-night-1947",
          "title": "The Long Night",
          "medium": "Watch TCM",
          "venue": null,
          "year": "1947"
        }
      ]
    },
    {
      "name": "Frank McHugh",
      "count": 5,
      "slug": null,
      "viewings": [
        {
          "sequence": 1323,
          "date": "2022-08-19",
          "slug": "the-hoodlum-saint-1946",
          "title": "The Hoodlum Saint",
          "medium": "Watch TCM",
          "venue": null,
          "year": "1946"
        },
        {
          "sequence": 1324,
          "date": "2022-08-20",
          "slug": "virginia-city-1940",
          "title": "Virginia City",
          "medium": "Watch TCM",
          "venue": null,
          "year": "1940"
        },
        {
          "sequence": 1363,
          "date": "2022-09-26",
          "slug": null,
          "title": "I Love You Again",
          "medium": "Watch TCM",
          "venue": null,
          "year": "1940"
        },
        {
          "sequence": 1370,
          "date": "2022-10-03",
          "slug": "swing-your-lady-1938",
          "title": "Swing Your Lady",
          "medium": "Watch TCM",
          "venue": null,
          "year": "1938"
        },
        {
          "sequence": 1378,
          "date": "2022-10-12",
          "slug": null,
          "title": "The Roaring Twenties",
          "medium": "Watch TCM",
          "venue": null,
          "year": "1939"
        }
      ]
    },
    {
      "name": "Henry O'Neill",
      "count": 5,
      "slug": null,
      "viewings": [
        {
          "sequence": 1323,
          "date": "2022-08-19",
          "slug": "the-hoodlum-saint-1946",
          "title": "The Hoodlum Saint",
          "medium": "Watch TCM",
          "venue": null,
          "year": "1946"
        },
        {
          "sequence": 1341,
          "date": "2022-09-07",
          "slug": "invisible-stripes-1939",
          "title": "Invisible Stripes",
          "medium": "Watch TCM",
          "venue": null,
          "year": "1939"
        },
        {
          "sequence": 1351,
          "date": "2022-09-15",
          "slug": "holiday-affair-1949",
          "title": "Holiday Affair",
          "medium": "Watch TCM",
          "venue": null,
          "year": "1949"
        },
        {
          "sequence": 1371,
          "date": "2022-10-04",
          "slug": "two-against-the-world-1936",
          "title": "Two Against the World",
          "medium": "Watch TCM",
          "venue": null,
          "year": "1936"
        },
        {
          "sequence": 1379,
          "date": "2022-10-13",
          "slug": null,
          "title": "Racket Busters",
          "medium": "Watch TCM",
          "venue": null,
          "year": "1938"
        }
      ]
    },
    {
      "name": "Vincent Price",
      "count": 5,
      "slug": "vincent-price",
      "viewings": [
        {
          "sequence": 1327,
          "date": "2022-08-22",
          "slug": "dangerous-mission-1954",
          "title": "Dangerous Mission",
          "medium": "Watch TCM",
          "venue": null,
          "year": "1954"
        },
        {
          "sequence": 1338,
          "date": "2022-09-05",
          "slug": "the-three-musketeers-1948",
          "title": "The Three Musketeers",
          "medium": "Watch TCM",
          "venue": null,
          "year": "1948"
        },
        {
          "sequence": 1374,
          "date": "2022-10-05",
          "slug": null,
          "title": "Convicts 4",
          "medium": "Watch TCM",
          "venue": null,
          "year": "1962"
        },
        {
          "sequence": 1385,
          "date": "2022-10-16",
          "slug": "the-long-night-1947",
          "title": "The Long Night",
          "medium": "Watch TCM",
          "venue": null,
          "year": "1947"
        },
        {
          "sequence": 1402,
          "date": "2022-10-26",
          "slug": null,
          "title": "Dr. Goldfoot and the Bikini Machine",
          "medium": "Watch TCM",
          "venue": null,
          "year": "1965"
        }
      ]
    }
  ],
  "mostWatchedWriters": [
    {
      "name": "Wes Craven",
      "count": 5,
      "slug": null,
      "viewings": [
        {
          "sequence": 1228,
          "date": "2022-01-12",
          "slug": "the-hills-have-eyes-1977",
          "title": "The Hills Have Eyes",
          "medium": "4k UHD Blu-ray",
          "venue": null,
          "year": "1977"
        },
        {
          "sequence": 1230,
          "date": "2022-01-14",
          "slug": "deadly-blessing-1981",
          "title": "Deadly Blessing",
          "medium": "Blu-ray",
          "venue": null,
          "year": "1981"
        },
        {
          "sequence": 1235,
          "date": "2022-01-26",
          "slug": "swamp-thing-1982",
          "title": "Swamp Thing",
          "medium": "Amazon",
          "venue": null,
          "year": "1982"
        },
        {
          "sequence": 1241,
          "date": "2022-02-02",
          "slug": "the-hills-have-eyes-part-ii-1984",
          "title": "The Hills Have Eyes Part II",
          "medium": "Arrow Player",
          "venue": null,
          "year": "1984"
        },
        {
          "sequence": 1247,
          "date": "2022-02-09",
          "slug": "a-nightmare-on-elm-street-1984",
          "title": "A Nightmare on Elm Street",
          "medium": "Blu-ray",
          "venue": null,
          "year": "1984"
        }
      ]
    },
    {
      "name": "Rob Zombie",
      "count": 3,
      "slug": null,
      "viewings": [
        {
          "sequence": 1231,
          "date": "2022-01-17",
          "slug": "3-from-hell-2019",
          "title": "3 from Hell",
          "medium": "iTunes",
          "venue": null,
          "year": "2019"
        },
        {
          "sequence": 1267,
          "date": "2022-03-31",
          "slug": "halloween-2007",
          "title": "Halloween",
          "medium": "iTunes",
          "venue": null,
          "year": "2007"
        },
        {
          "sequence": 1268,
          "date": "2022-03-31",
          "slug": "halloween-ii-2009",
          "title": "Halloween II",
          "medium": "iTunes",
          "venue": null,
          "year": "2009"
        }
      ]
    },
    {
      "name": "Dudley Nichols",
      "count": 3,
      "slug": null,
      "viewings": [
        {
          "sequence": 1292,
          "date": "2022-06-21",
          "slug": "pilgrimage-1933",
          "title": "Pilgrimage",
          "medium": "Criterion Channel",
          "venue": null,
          "year": "1933"
        },
        {
          "sequence": 1293,
          "date": "2022-06-22",
          "slug": "steamboat-round-the-bend-1935",
          "title": "Steamboat Round the Bend",
          "medium": "Criterion Channel",
          "venue": null,
          "year": "1935"
        },
        {
          "sequence": 1294,
          "date": "2022-06-27",
          "slug": "the-plough-and-the-stars-1936",
          "title": "The Plough and the Stars",
          "medium": "Criterion Channel",
          "venue": null,
          "year": "1936"
        }
      ]
    },
    {
      "name": "Leigh Whannell",
      "count": 3,
      "slug": null,
      "viewings": [
        {
          "sequence": 1301,
          "date": "2022-07-08",
          "slug": "saw-2004",
          "title": "Saw",
          "medium": "Blu-ray",
          "venue": null,
          "year": "2004"
        },
        {
          "sequence": 1305,
          "date": "2022-07-22",
          "slug": "saw-ii-2005",
          "title": "Saw II",
          "medium": "Blu-ray",
          "venue": null,
          "year": "2005"
        },
        {
          "sequence": 1307,
          "date": "2022-07-28",
          "slug": "saw-iii-2006",
          "title": "Saw III",
          "medium": "Blu-ray",
          "venue": null,
          "year": "2006"
        }
      ]
    },
    {
      "name": "Patrick Melton",
      "count": 3,
      "slug": null,
      "viewings": [
        {
          "sequence": 1315,
          "date": "2022-08-10",
          "slug": "saw-iv-2007",
          "title": "Saw IV",
          "medium": "Blu-ray",
          "venue": null,
          "year": "2007"
        },
        {
          "sequence": 1319,
          "date": "2022-08-12",
          "slug": "saw-v-2008",
          "title": "Saw V",
          "medium": "Blu-ray",
          "venue": null,
          "year": "2008"
        },
        {
          "sequence": 1346,
          "date": "2022-09-10",
          "slug": "saw-vi-2009",
          "title": "Saw VI",
          "medium": "Blu-ray",
          "venue": null,
          "year": "2009"
        }
      ]
    },
    {
      "name": "Marcus Dunstan",
      "count": 3,
      "slug": null,
      "viewings": [
        {
          "sequence": 1315,
          "date": "2022-08-10",
          "slug": "saw-iv-2007",
          "title": "Saw IV",
          "medium": "Blu-ray",
          "venue": null,
          "year": "2007"
        },
        {
          "sequence": 1319,
          "date": "2022-08-12",
          "slug": "saw-v-2008",
          "title": "Saw V",
          "medium": "Blu-ray",
          "venue": null,
          "year": "2008"
        },
        {
          "sequence": 1346,
          "date": "2022-09-10",
          "slug": "saw-vi-2009",
          "title": "Saw VI",
          "medium": "Blu-ray",
          "venue": null,
          "year": "2009"
        }
      ]
    },
    {
      "name": "W.R. Burnett",
      "count": 3,
      "slug": null,
      "viewings": [
        {
          "sequence": 1327,
          "date": "2022-08-22",
          "slug": "dangerous-mission-1954",
          "title": "Dangerous Mission",
          "medium": "Watch TCM",
          "venue": null,
          "year": "1954"
        },
        {
          "sequence": 1344,
          "date": "2022-09-09",
          "slug": "king-of-the-underworld-1939",
          "title": "King of the Underworld",
          "medium": "Watch TCM",
          "venue": null,
          "year": "1939"
        },
        {
          "sequence": 1349,
          "date": "2022-09-13",
          "slug": "high-sierra-1941",
          "title": "High Sierra",
          "medium": "Watch TCM",
          "venue": null,
          "year": "1940"
        }
      ]
    },
    {
      "name": "Casey Robinson",
      "count": 3,
      "slug": null,
      "viewings": [
        {
          "sequence": 1342,
          "date": "2022-09-07",
          "slug": "the-corn-is-green-1945",
          "title": "The Corn Is Green",
          "medium": "Watch TCM",
          "venue": null,
          "year": "1945"
        },
        {
          "sequence": 1377,
          "date": "2022-10-10",
          "slug": null,
          "title": "Now, Voyager",
          "medium": "Watch TCM",
          "venue": null,
          "year": "1942"
        },
        {
          "sequence": 1390,
          "date": "2022-10-21",
          "slug": null,
          "title": "It's Love I'm After",
          "medium": "Watch TCM",
          "venue": null,
          "year": "1937"
        }
      ]
    },
    {
      "name": "Julia Ducournau",
      "count": 2,
      "slug": null,
      "viewings": [
        {
          "sequence": 1226,
          "date": "2022-01-09",
          "slug": "raw-2016",
          "title": "Raw",
          "medium": "Netflix",
          "venue": null,
          "year": "2016"
        },
        {
          "sequence": 1232,
          "date": "2022-01-20",
          "slug": "titane-2021",
          "title": "Titane",
          "medium": "iTunes",
          "venue": null,
          "year": "2021"
        }
      ]
    },
    {
      "name": "Philip Eisner",
      "count": 2,
      "slug": null,
      "viewings": [
        {
          "sequence": 1236,
          "date": "2022-01-28",
          "slug": "event-horizon-1997",
          "title": "Event Horizon",
          "medium": "HBO Max",
          "venue": null,
          "year": "1997"
        },
        {
          "sequence": 1277,
          "date": "2022-05-29",
          "slug": "event-horizon-1997",
          "title": "Event Horizon",
          "medium": "35mm",
          "venue": "Prince Charles Cinema",
          "year": "1997"
        }
      ]
    }
  ]
}