{"most_watched": [{"imdb_id": "nm0000406", "full_name": "John Ford", "slug": "john-ford", "movie_count": 20, "viewings": [{"date": "2012-01-25", "venue": "TCM HD", "sequence": 28, "movie": {"imdb_id": "tt0026008", "title": "The World Moves On", "year": 1934, "decade": "1930s", "slug": null}, "person": {"imdb_id": "nm0000406", "full_name": "John Ford", "slug": "john-ford"}}, {"date": "2012-01-28", "venue": "TCM HD", "sequence": 45, "movie": {"imdb_id": "tt0054292", "title": "Sergeant Rutledge", "year": 1960, "decade": "1960s", "slug": null}, "person": {"imdb_id": "nm0000406", "full_name": "John Ford", "slug": "john-ford"}}, {"date": "2012-02-10", "venue": "TCM HD", "sequence": 68, "movie": {"imdb_id": "tt0032728", "title": "The Long Voyage Home", "year": 1940, "decade": "1940s", "slug": null}, "person": {"imdb_id": "nm0000406", "full_name": "John Ford", "slug": "john-ford"}}, {"date": "2012-02-15", "venue": "TCM HD", "sequence": 76, "movie": {"imdb_id": "tt0038160", "title": "They Were Expendable", "year": 1945, "decade": "1940s", "slug": null}, "person": {"imdb_id": "nm0000406", "full_name": "John Ford", "slug": "john-ford"}}, {"date": "2012-02-19", "venue": "TCM HD", "sequence": 82, "movie": {"imdb_id": "tt0046085", "title": "Mogambo", "year": 1953, "decade": "1950s", "slug": null}, "person": {"imdb_id": "nm0000406", "full_name": "John Ford", "slug": "john-ford"}}, {"date": "2012-02-24", "venue": "TCM HD", "sequence": 86, "movie": {"imdb_id": "tt0021622", "title": "Arrowsmith", "year": 1931, "decade": "1930s", "slug": null}, "person": {"imdb_id": "nm0000406", "full_name": "John Ford", "slug": "john-ford"}}, {"date": "2012-03-12", "venue": "TCM HD", "sequence": 113, "movie": {"imdb_id": "tt0029030", "title": "The Hurricane", "year": 1937, "decade": "1930s", "slug": null}, "person": {"imdb_id": "nm0000406", "full_name": "John Ford", "slug": "john-ford"}}, {"date": "2012-03-30", "venue": "TCM HD", "sequence": 134, "movie": {"imdb_id": "tt0027214", "title": "The Whole Town's Talking", "year": 1935, "decade": "1930s", "slug": null}, "person": {"imdb_id": "nm0000406", "full_name": "John Ford", "slug": "john-ford"}}, {"date": "2012-03-31", "venue": "TCM HD", "sequence": 137, "movie": {"imdb_id": "tt0027948", "title": "Mary of Scotland", "year": 1936, "decade": "1930s", "slug": null}, "person": {"imdb_id": "nm0000406", "full_name": "John Ford", "slug": "john-ford"}}, {"date": "2012-03-31", "venue": "TCM HD", "sequence": 138, "movie": {"imdb_id": "tt0050902", "title": "The Rising of the Moon", "year": 1957, "decade": "1950s", "slug": null}, "person": {"imdb_id": "nm0000406", "full_name": "John Ford", "slug": "john-ford"}}, {"date": "2012-04-01", "venue": "TCM HD", "sequence": 139, "movie": {"imdb_id": "tt0051845", "title": "The Last Hurrah", "year": 1958, "decade": "1950s", "slug": null}, "person": {"imdb_id": "nm0000406", "full_name": "John Ford", "slug": "john-ford"}}, {"date": "2012-04-06", "venue": "TCM HD", "sequence": 143, "movie": {"imdb_id": "tt0031971", "title": "Stagecoach", "year": 1939, "decade": "1930s", "slug": null}, "person": {"imdb_id": "nm0000406", "full_name": "John Ford", "slug": "john-ford"}}, {"date": "2015-06-10", "venue": "Alamo Drafthouse Cinema - One Loudoun", "sequence": 500, "movie": {"imdb_id": "tt0049730", "title": "The Searchers", "year": 1956, "decade": "1950s", "slug": null}, "person": {"imdb_id": "nm0000406", "full_name": "John Ford", "slug": "john-ford"}}, {"date": "2018-04-17", "venue": "TCM", "sequence": 664, "movie": {"imdb_id": "tt0028141", "title": "The Prisoner of Shark Island", "year": 1936, "decade": "1930s", "slug": null}, "person": {"imdb_id": "nm0000406", "full_name": "John Ford", "slug": "john-ford"}}, {"date": "2019-06-16", "venue": "Alamo Drafthouse Cinema - One Loudoun", "sequence": 757, "movie": {"imdb_id": "tt0031971", "title": "Stagecoach", "year": 1939, "decade": "1930s", "slug": null}, "person": {"imdb_id": "nm0000406", "full_name": "John Ford", "slug": "john-ford"}}, {"date": "2020-07-12", "venue": "iTunes", "sequence": 839, "movie": {"imdb_id": "tt0019699", "title": "The Black Watch", "year": 1929, "decade": "1920s", "slug": "the-black-watch-1929"}, "person": {"imdb_id": "nm0000406", "full_name": "John Ford", "slug": "john-ford"}}, {"date": "2020-09-11", "venue": "iTunes", "sequence": 866, "movie": {"imdb_id": "tt0020702", "title": "Born Reckless", "year": 1930, "decade": "1930s", "slug": "born-reckless-1930"}, "person": {"imdb_id": "nm0000406", "full_name": "John Ford", "slug": "john-ford"}}, {"date": "2020-09-11", "venue": "iTunes", "sequence": 867, "movie": {"imdb_id": "tt0021140", "title": "Men Without Women", "year": 1930, "decade": "1930s", "slug": "men-without-women-1930"}, "person": {"imdb_id": "nm0000406", "full_name": "John Ford", "slug": "john-ford"}}, {"date": "2020-10-09", "venue": "RareFilm.net", "sequence": 882, "movie": {"imdb_id": "tt0020359", "title": "Salute", "year": 1929, "decade": "1920s", "slug": "salute-1929"}, "person": {"imdb_id": "nm0000406", "full_name": "John Ford", "slug": "john-ford"}}, {"date": "2020-11-06", "venue": "iTunes", "sequence": 911, "movie": {"imdb_id": "tt0021508", "title": "Up the River", "year": 1930, "decade": "1930s", "slug": "up-the-river-1930"}, "person": {"imdb_id": "nm0000406", "full_name": "John Ford", "slug": "john-ford"}}, {"date": "2021-01-07", "venue": "iTunes", "sequence": 974, "movie": {"imdb_id": "tt0022353", "title": "Seas Beneath", "year": 1931, "decade": "1930s", "slug": "seas-beneath-1931"}, "person": {"imdb_id": "nm0000406", "full_name": "John Ford", "slug": "john-ford"}}], "viewing_count": 21}, {"imdb_id": "nm0751577", "full_name": "Anthony Russo", "slug": null, "movie_count": 4, "viewings": [{"date": "2014-04-10", "venue": "AMC Tysons Corner 16", "sequence": 379, "movie": {"imdb_id": "tt1843866", "title": "Captain America: The Winter Soldier", "year": 2014, "decade": "2010s", "slug": null}, "person": {"imdb_id": "nm0751577", "full_name": "Anthony Russo", "slug": null}}, {"date": "2015-01-04", "venue": "Blu-ray", "sequence": 465, "movie": {"imdb_id": "tt1843866", "title": "Captain America: The Winter Soldier", "year": 2014, "decade": "2010s", "slug": null}, "person": {"imdb_id": "nm0751577", "full_name": "Anthony Russo", "slug": null}}, {"date": "2016-05-12", "venue": "Alamo Drafthouse Cinema - One Loudoun", "sequence": 547, "movie": {"imdb_id": "tt3498820", "title": "Captain America: Civil War", "year": 2016, "decade": "2010s", "slug": "captain-america-civil-war-2016"}, "person": {"imdb_id": "nm0751577", "full_name": "Anthony Russo", "slug": null}}, {"date": "2016-11-12", "venue": "Amazon", "sequence": 569, "movie": {"imdb_id": "tt3498820", "title": "Captain America: Civil War", "year": 2016, "decade": "2010s", "slug": "captain-america-civil-war-2016"}, "person": {"imdb_id": "nm0751577", "full_name": "Anthony Russo", "slug": null}}, {"date": "2018-05-18", "venue": "Alamo Drafthouse Cinema - One Loudoun", "sequence": 677, "movie": {"imdb_id": "tt4154756", "title": "Avengers: Infinity War", "year": 2018, "decade": "2010s", "slug": "avengers-infinity-war-2018"}, "person": {"imdb_id": "nm0751577", "full_name": "Anthony Russo", "slug": null}}, {"date": "2018-05-22", "venue": "Alamo Drafthouse Cinema - One Loudoun", "sequence": 679, "movie": {"imdb_id": "tt4154756", "title": "Avengers: Infinity War", "year": 2018, "decade": "2010s", "slug": "avengers-infinity-war-2018"}, "person": {"imdb_id": "nm0751577", "full_name": "Anthony Russo", "slug": null}}, {"date": "2018-05-27", "venue": "Alamo Drafthouse Cinema - One Loudoun", "sequence": 681, "movie": {"imdb_id": "tt4154756", "title": "Avengers: Infinity War", "year": 2018, "decade": "2010s", "slug": "avengers-infinity-war-2018"}, "person": {"imdb_id": "nm0751577", "full_name": "Anthony Russo", "slug": null}}, {"date": "2018-06-13", "venue": "Alamo Drafthouse Cinema - One Loudoun", "sequence": 683, "movie": {"imdb_id": "tt4154756", "title": "Avengers: Infinity War", "year": 2018, "decade": "2010s", "slug": "avengers-infinity-war-2018"}, "person": {"imdb_id": "nm0751577", "full_name": "Anthony Russo", "slug": null}}, {"date": "2019-05-13", "venue": "Alamo Drafthouse Cinema - One Loudoun", "sequence": 750, "movie": {"imdb_id": "tt4154796", "title": "Avengers: Endgame", "year": 2019, "decade": "2010s", "slug": "avengers-endgame-2019"}, "person": {"imdb_id": "nm0751577", "full_name": "Anthony Russo", "slug": null}}, {"date": "2019-05-16", "venue": "Alamo Drafthouse Cinema - One Loudoun", "sequence": 751, "movie": {"imdb_id": "tt4154796", "title": "Avengers: Endgame", "year": 2019, "decade": "2010s", "slug": "avengers-endgame-2019"}, "person": {"imdb_id": "nm0751577", "full_name": "Anthony Russo", "slug": null}}, {"date": "2019-06-03", "venue": "Alamo Drafthouse Cinema - One Loudoun", "sequence": 756, "movie": {"imdb_id": "tt4154796", "title": "Avengers: Endgame", "year": 2019, "decade": "2010s", "slug": "avengers-endgame-2019"}, "person": {"imdb_id": "nm0751577", "full_name": "Anthony Russo", "slug": null}}, {"date": "2020-03-28", "venue": "4k UHD Blu-ray", "sequence": 823, "movie": {"imdb_id": "tt4154756", "title": "Avengers: Infinity War", "year": 2018, "decade": "2010s", "slug": "avengers-infinity-war-2018"}, "person": {"imdb_id": "nm0751577", "full_name": "Anthony Russo", "slug": null}}, {"date": "2020-06-13", "venue": "4k UHD Blu-ray", "sequence": 833, "movie": {"imdb_id": "tt1843866", "title": "Captain America: The Winter Soldier", "year": 2014, "decade": "2010s", "slug": null}, "person": {"imdb_id": "nm0751577", "full_name": "Anthony Russo", "slug": null}}, {"date": "2020-07-25", "venue": "4k UHD Blu-ray", "sequence": 843, "movie": {"imdb_id": "tt3498820", "title": "Captain America: Civil War", "year": 2016, "decade": "2010s", "slug": "captain-america-civil-war-2016"}, "person": {"imdb_id": "nm0751577", "full_name": "Anthony Russo", "slug": null}}, {"date": "2020-10-17", "venue": "4k UHD Blu-ray", "sequence": 892, "movie": {"imdb_id": "tt4154756", "title": "Avengers: Infinity War", "year": 2018, "decade": "2010s", "slug": "avengers-infinity-war-2018"}, "person": {"imdb_id": "nm0751577", "full_name": "Anthony Russo", "slug": null}}, {"date": "2020-11-14", "venue": "4k UHD Blu-ray", "sequence": 917, "movie": {"imdb_id": "tt4154796", "title": "Avengers: Endgame", "year": 2019, "decade": "2010s", "slug": "avengers-endgame-2019"}, "person": {"imdb_id": "nm0751577", "full_name": "Anthony Russo", "slug": null}}], "viewing_count": 16}, {"imdb_id": "nm0751648", "full_name": "Joe Russo", "slug": null, "movie_count": 4, "viewings": [{"date": "2014-04-10", "venue": "AMC Tysons Corner 16", "sequence": 379, "movie": {"imdb_id": "tt1843866", "title": "Captain America: The Winter Soldier", "year": 2014, "decade": "2010s", "slug": null}, "person": {"imdb_id": "nm0751648", "full_name": "Joe Russo", "slug": null}}, {"date": "2015-01-04", "venue": "Blu-ray", "sequence": 465, "movie": {"imdb_id": "tt1843866", "title": "Captain America: The Winter Soldier", "year": 2014, "decade": "2010s", "slug": null}, "person": {"imdb_id": "nm0751648", "full_name": "Joe Russo", "slug": null}}, {"date": "2016-05-12", "venue": "Alamo Drafthouse Cinema - One Loudoun", "sequence": 547, "movie": {"imdb_id": "tt3498820", "title": "Captain America: Civil War", "year": 2016, "decade": "2010s", "slug": "captain-america-civil-war-2016"}, "person": {"imdb_id": "nm0751648", "full_name": "Joe Russo", "slug": null}}, {"date": "2016-11-12", "venue": "Amazon", "sequence": 569, "movie": {"imdb_id": "tt3498820", "title": "Captain America: Civil War", "year": 2016, "decade": "2010s", "slug": "captain-america-civil-war-2016"}, "person": {"imdb_id": "nm0751648", "full_name": "Joe Russo", "slug": null}}, {"date": "2018-05-18", "venue": "Alamo Drafthouse Cinema - One Loudoun", "sequence": 677, "movie": {"imdb_id": "tt4154756", "title": "Avengers: Infinity War", "year": 2018, "decade": "2010s", "slug": "avengers-infinity-war-2018"}, "person": {"imdb_id": "nm0751648", "full_name": "Joe Russo", "slug": null}}, {"date": "2018-05-22", "venue": "Alamo Drafthouse Cinema - One Loudoun", "sequence": 679, "movie": {"imdb_id": "tt4154756", "title": "Avengers: Infinity War", "year": 2018, "decade": "2010s", "slug": "avengers-infinity-war-2018"}, "person": {"imdb_id": "nm0751648", "full_name": "Joe Russo", "slug": null}}, {"date": "2018-05-27", "venue": "Alamo Drafthouse Cinema - One Loudoun", "sequence": 681, "movie": {"imdb_id": "tt4154756", "title": "Avengers: Infinity War", "year": 2018, "decade": "2010s", "slug": "avengers-infinity-war-2018"}, "person": {"imdb_id": "nm0751648", "full_name": "Joe Russo", "slug": null}}, {"date": "2018-06-13", "venue": "Alamo Drafthouse Cinema - One Loudoun", "sequence": 683, "movie": {"imdb_id": "tt4154756", "title": "Avengers: Infinity War", "year": 2018, "decade": "2010s", "slug": "avengers-infinity-war-2018"}, "person": {"imdb_id": "nm0751648", "full_name": "Joe Russo", "slug": null}}, {"date": "2019-05-13", "venue": "Alamo Drafthouse Cinema - One Loudoun", "sequence": 750, "movie": {"imdb_id": "tt4154796", "title": "Avengers: Endgame", "year": 2019, "decade": "2010s", "slug": "avengers-endgame-2019"}, "person": {"imdb_id": "nm0751648", "full_name": "Joe Russo", "slug": null}}, {"date": "2019-05-16", "venue": "Alamo Drafthouse Cinema - One Loudoun", "sequence": 751, "movie": {"imdb_id": "tt4154796", "title": "Avengers: Endgame", "year": 2019, "decade": "2010s", "slug": "avengers-endgame-2019"}, "person": {"imdb_id": "nm0751648", "full_name": "Joe Russo", "slug": null}}, {"date": "2019-06-03", "venue": "Alamo Drafthouse Cinema - One Loudoun", "sequence": 756, "movie": {"imdb_id": "tt4154796", "title": "Avengers: Endgame", "year": 2019, "decade": "2010s", "slug": "avengers-endgame-2019"}, "person": {"imdb_id": "nm0751648", "full_name": "Joe Russo", "slug": null}}, {"date": "2020-03-28", "venue": "4k UHD Blu-ray", "sequence": 823, "movie": {"imdb_id": "tt4154756", "title": "Avengers: Infinity War", "year": 2018, "decade": "2010s", "slug": "avengers-infinity-war-2018"}, "person": {"imdb_id": "nm0751648", "full_name": "Joe Russo", "slug": null}}, {"date": "2020-06-13", "venue": "4k UHD Blu-ray", "sequence": 833, "movie": {"imdb_id": "tt1843866", "title": "Captain America: The Winter Soldier", "year": 2014, "decade": "2010s", "slug": null}, "person": {"imdb_id": "nm0751648", "full_name": "Joe Russo", "slug": null}}, {"date": "2020-07-25", "venue": "4k UHD Blu-ray", "sequence": 843, "movie": {"imdb_id": "tt3498820", "title": "Captain America: Civil War", "year": 2016, "decade": "2010s", "slug": "captain-america-civil-war-2016"}, "person": {"imdb_id": "nm0751648", "full_name": "Joe Russo", "slug": null}}, {"date": "2020-10-17", "venue": "4k UHD Blu-ray", "sequence": 892, "movie": {"imdb_id": "tt4154756", "title": "Avengers: Infinity War", "year": 2018, "decade": "2010s", "slug": "avengers-infinity-war-2018"}, "person": {"imdb_id": "nm0751648", "full_name": "Joe Russo", "slug": null}}, {"date": "2020-11-14", "venue": "4k UHD Blu-ray", "sequence": 917, "movie": {"imdb_id": "tt4154796", "title": "Avengers: Endgame", "year": 2019, "decade": "2010s", "slug": "avengers-endgame-2019"}, "person": {"imdb_id": "nm0751648", "full_name": "Joe Russo", "slug": null}}], "viewing_count": 16}, {"imdb_id": "nm0000118", "full_name": "John Carpenter", "slug": null, "movie_count": 8, "viewings": [{"date": "2012-01-20", "venue": "TCM HD", "sequence": 23, "movie": {"imdb_id": "tt0096256", "title": "They Live", "year": 1988, "decade": "1980s", "slug": null}, "person": {"imdb_id": "nm0000118", "full_name": "John Carpenter", "slug": null}}, {"date": "2012-03-24", "venue": "Blu-ray", "sequence": 122, "movie": {"imdb_id": "tt0090728", "title": "Big Trouble in Little China", "year": 1986, "decade": "1980s", "slug": null}, "person": {"imdb_id": "nm0000118", "full_name": "John Carpenter", "slug": null}}, {"date": "2012-03-24", "venue": "Encore HD", "sequence": 123, "movie": {"imdb_id": "tt0113409", "title": "In the Mouth of Madness", "year": 1995, "decade": "1990s", "slug": null}, "person": {"imdb_id": "nm0000118", "full_name": "John Carpenter", "slug": null}}, {"date": "2012-05-05", "venue": "TCM HD", "sequence": 176, "movie": {"imdb_id": "tt0082340", "title": "Escape from New York", "year": 1981, "decade": "1980s", "slug": null}, "person": {"imdb_id": "nm0000118", "full_name": "John Carpenter", "slug": null}}, {"date": "2012-07-02", "venue": "The Black Cat", "sequence": 194, "movie": {"imdb_id": "tt0084787", "title": "The Thing", "year": 1982, "decade": "1980s", "slug": null}, "person": {"imdb_id": "nm0000118", "full_name": "John Carpenter", "slug": null}}, {"date": "2012-10-30", "venue": "Landmark E Street Cinema", "sequence": 235, "movie": {"imdb_id": "tt0077651", "title": "Halloween", "year": 1978, "decade": "1970s", "slug": null}, "person": {"imdb_id": "nm0000118", "full_name": "John Carpenter", "slug": null}}, {"date": "2013-01-20", "venue": "Netflix", "sequence": 268, "movie": {"imdb_id": "tt0093777", "title": "Prince of Darkness", "year": 1987, "decade": "1980s", "slug": null}, "person": {"imdb_id": "nm0000118", "full_name": "John Carpenter", "slug": null}}, {"date": "2013-08-08", "venue": "Alamo Drafthouse Cinema - One Loudoun", "sequence": 309, "movie": {"imdb_id": "tt0082340", "title": "Escape from New York", "year": 1981, "decade": "1980s", "slug": null}, "person": {"imdb_id": "nm0000118", "full_name": "John Carpenter", "slug": null}}, {"date": "2014-01-25", "venue": "Netflix", "sequence": 365, "movie": {"imdb_id": "tt0074156", "title": "Assault on Precinct 13", "year": 1976, "decade": "1970s", "slug": null}, "person": {"imdb_id": "nm0000118", "full_name": "John Carpenter", "slug": null}}, {"date": "2015-02-13", "venue": "Blu-ray", "sequence": 478, "movie": {"imdb_id": "tt0077651", "title": "Halloween", "year": 1978, "decade": "1970s", "slug": null}, "person": {"imdb_id": "nm0000118", "full_name": "John Carpenter", "slug": null}}, {"date": "2018-08-13", "venue": "Alamo Drafthouse Cinema - One Loudoun", "sequence": 696, "movie": {"imdb_id": "tt0096256", "title": "They Live", "year": 1988, "decade": "1980s", "slug": null}, "person": {"imdb_id": "nm0000118", "full_name": "John Carpenter", "slug": null}}, {"date": "2018-10-27", "venue": "Alamo Drafthouse Cinema - Woodbridge", "sequence": 713, "movie": {"imdb_id": "tt0093777", "title": "Prince of Darkness", "year": 1987, "decade": "1980s", "slug": null}, "person": {"imdb_id": "nm0000118", "full_name": "John Carpenter", "slug": null}}, {"date": "2019-01-31", "venue": "Shudder", "sequence": 728, "movie": {"imdb_id": "tt0077651", "title": "Halloween", "year": 1978, "decade": "1970s", "slug": null}, "person": {"imdb_id": "nm0000118", "full_name": "John Carpenter", "slug": null}}, {"date": "2020-03-08", "venue": "Alamo Drafthouse Cinema - One Loudoun", "sequence": 818, "movie": {"imdb_id": "tt0084787", "title": "The Thing", "year": 1982, "decade": "1980s", "slug": null}, "person": {"imdb_id": "nm0000118", "full_name": "John Carpenter", "slug": null}}], "viewing_count": 14}, {"imdb_id": "nm0001328", "full_name": "Howard Hawks", "slug": "howard-hawks", "movie_count": 11, "viewings": [{"date": "2012-02-10", "venue": "TCM HD", "sequence": 69, "movie": {"imdb_id": "tt0044419", "title": "The Big Sky", "year": 1952, "decade": "1950s", "slug": null}, "person": {"imdb_id": "nm0001328", "full_name": "Howard Hawks", "slug": "howard-hawks"}}, {"date": "2012-02-15", "venue": "TCM HD", "sequence": 75, "movie": {"imdb_id": "tt0035616", "title": "Air Force", "year": 1943, "decade": "1940s", "slug": null}, "person": {"imdb_id": "nm0001328", "full_name": "Howard Hawks", "slug": "howard-hawks"}}, {"date": "2012-02-25", "venue": "TCM HD", "sequence": 90, "movie": {"imdb_id": "tt0031762", "title": "Only Angels Have Wings", "year": 1939, "decade": "1930s", "slug": null}, "person": {"imdb_id": "nm0001328", "full_name": "Howard Hawks", "slug": "howard-hawks"}}, {"date": "2012-03-26", "venue": "TCM HD", "sequence": 130, "movie": {"imdb_id": "tt0041498", "title": "I Was a Male War Bride", "year": 1949, "decade": "1940s", "slug": null}, "person": {"imdb_id": "nm0001328", "full_name": "Howard Hawks", "slug": "howard-hawks"}}, {"date": "2012-04-27", "venue": "Landmark E Street Cinema", "sequence": 171, "movie": {"imdb_id": "tt0038355", "title": "The Big Sleep", "year": 1946, "decade": "1940s", "slug": null}, "person": {"imdb_id": "nm0001328", "full_name": "Howard Hawks", "slug": "howard-hawks"}}, {"date": "2012-04-28", "venue": "Landmark E Street Cinema", "sequence": 172, "movie": {"imdb_id": "tt0038355", "title": "The Big Sleep", "year": 1946, "decade": "1940s", "slug": null}, "person": {"imdb_id": "nm0001328", "full_name": "Howard Hawks", "slug": "howard-hawks"}}, {"date": "2013-03-23", "venue": "Netflix", "sequence": 293, "movie": {"imdb_id": "tt0061619", "title": "El Dorado", "year": 1966, "decade": "1960s", "slug": null}, "person": {"imdb_id": "nm0001328", "full_name": "Howard Hawks", "slug": "howard-hawks"}}, {"date": "2017-06-18", "venue": "Alamo Drafthouse Cinema - One Loudoun", "sequence": 598, "movie": {"imdb_id": "tt0053221", "title": "Rio Bravo", "year": 1959, "decade": "1950s", "slug": null}, "person": {"imdb_id": "nm0001328", "full_name": "Howard Hawks", "slug": "howard-hawks"}}, {"date": "2017-12-09", "venue": "Blu-ray", "sequence": 622, "movie": {"imdb_id": "tt0053221", "title": "Rio Bravo", "year": 1959, "decade": "1950s", "slug": null}, "person": {"imdb_id": "nm0001328", "full_name": "Howard Hawks", "slug": "howard-hawks"}}, {"date": "2018-03-28", "venue": "TCM", "sequence": 657, "movie": {"imdb_id": "tt0022792", "title": "The Crowd Roars", "year": 1932, "decade": "1930s", "slug": null}, "person": {"imdb_id": "nm0001328", "full_name": "Howard Hawks", "slug": "howard-hawks"}}, {"date": "2018-05-01", "venue": "DVD", "sequence": 671, "movie": {"imdb_id": "tt0048283", "title": "Land of the Pharaohs", "year": 1955, "decade": "1950s", "slug": null}, "person": {"imdb_id": "nm0001328", "full_name": "Howard Hawks", "slug": "howard-hawks"}}, {"date": "2018-06-17", "venue": "Blu-ray", "sequence": 686, "movie": {"imdb_id": "tt0053221", "title": "Rio Bravo", "year": 1959, "decade": "1950s", "slug": null}, "person": {"imdb_id": "nm0001328", "full_name": "Howard Hawks", "slug": "howard-hawks"}}, {"date": "2020-09-13", "venue": "iTunes", "sequence": 868, "movie": {"imdb_id": "tt0020815", "title": "The Dawn Patrol", "year": 1930, "decade": "1930s", "slug": "the-dawn-patrol-1930"}, "person": {"imdb_id": "nm0001328", "full_name": "Howard Hawks", "slug": "howard-hawks"}}, {"date": "2020-11-18", "venue": "DVD", "sequence": 918, "movie": {"imdb_id": "tt0021770", "title": "The Criminal Code", "year": 1930, "decade": "1930s", "slug": "the-criminal-code-1930"}, "person": {"imdb_id": "nm0001328", "full_name": "Howard Hawks", "slug": "howard-hawks"}}], "viewing_count": 14}, {"imdb_id": "nm0279807", "full_name": "Terence Fisher", "slug": null, "movie_count": 7, "viewings": [{"date": "2012-01-15", "venue": "TCM HD", "sequence": 20, "movie": {"imdb_id": "tt0058155", "title": "The Gorgon", "year": 1964, "decade": "1960s", "slug": null}, "person": {"imdb_id": "nm0279807", "full_name": "Terence Fisher", "slug": null}}, {"date": "2012-08-10", "venue": "Netflix", "sequence": 213, "movie": {"imdb_id": "tt0071519", "title": "Frankenstein and the Monster from Hell", "year": 1974, "decade": "1970s", "slug": null}, "person": {"imdb_id": "nm0279807", "full_name": "Terence Fisher", "slug": null}}, {"date": "2012-10-28", "venue": "TCM HD", "sequence": 233, "movie": {"imdb_id": "tt0052905", "title": "The Hound of the Baskervilles", "year": 1959, "decade": "1950s", "slug": null}, "person": {"imdb_id": "nm0279807", "full_name": "Terence Fisher", "slug": null}}, {"date": "2012-11-02", "venue": "TCM HD", "sequence": 240, "movie": {"imdb_id": "tt0062885", "title": "The Devil Rides Out", "year": 1968, "decade": "1960s", "slug": null}, "person": {"imdb_id": "nm0279807", "full_name": "Terence Fisher", "slug": null}}, {"date": "2012-11-03", "venue": "TCM HD", "sequence": 242, "movie": {"imdb_id": "tt0059127", "title": "Dracula: Prince of Darkness", "year": 1966, "decade": "1960s", "slug": null}, "person": {"imdb_id": "nm0279807", "full_name": "Terence Fisher", "slug": null}}, {"date": "2014-08-16", "venue": "DVD", "sequence": 418, "movie": {"imdb_id": "tt0051554", "title": "Horror of Dracula", "year": 1958, "decade": "1950s", "slug": "horror-of-dracula-1958"}, "person": {"imdb_id": "nm0279807", "full_name": "Terence Fisher", "slug": null}}, {"date": "2014-12-20", "venue": "Blu-ray", "sequence": 456, "movie": {"imdb_id": "tt0051554", "title": "Horror of Dracula", "year": 1958, "decade": "1950s", "slug": "horror-of-dracula-1958"}, "person": {"imdb_id": "nm0279807", "full_name": "Terence Fisher", "slug": null}}, {"date": "2015-01-17", "venue": "DVD", "sequence": 471, "movie": {"imdb_id": "tt0062885", "title": "The Devil Rides Out", "year": 1968, "decade": "1960s", "slug": null}, "person": {"imdb_id": "nm0279807", "full_name": "Terence Fisher", "slug": null}}, {"date": "2015-10-24", "venue": "Blu-ray", "sequence": 527, "movie": {"imdb_id": "tt0050280", "title": "The Curse of Frankenstein", "year": 1957, "decade": "1950s", "slug": "the-curse-of-frankenstein-1957"}, "person": {"imdb_id": "nm0279807", "full_name": "Terence Fisher", "slug": null}}, {"date": "2018-12-25", "venue": "Blu-ray", "sequence": 721, "movie": {"imdb_id": "tt0051554", "title": "Horror of Dracula", "year": 1958, "decade": "1950s", "slug": "horror-of-dracula-1958"}, "person": {"imdb_id": "nm0279807", "full_name": "Terence Fisher", "slug": null}}, {"date": "2020-09-19", "venue": "Blu-ray", "sequence": 871, "movie": {"imdb_id": "tt0050280", "title": "The Curse of Frankenstein", "year": 1957, "decade": "1950s", "slug": "the-curse-of-frankenstein-1957"}, "person": {"imdb_id": "nm0279807", "full_name": "Terence Fisher", "slug": null}}, {"date": "2020-12-08", "venue": "Blu-ray", "sequence": 935, "movie": {"imdb_id": "tt0051554", "title": "Horror of Dracula", "year": 1958, "decade": "1950s", "slug": "horror-of-dracula-1958"}, "person": {"imdb_id": "nm0279807", "full_name": "Terence Fisher", "slug": null}}], "viewing_count": 12}, {"imdb_id": "nm0000033", "full_name": "Alfred Hitchcock", "slug": "alfred-hitchcock", "movie_count": 11, "viewings": [{"date": "2012-02-04", "venue": "TCM HD", "sequence": 59, "movie": {"imdb_id": "tt0034248", "title": "Suspicion", "year": 1941, "decade": "1940s", "slug": null}, "person": {"imdb_id": "nm0000033", "full_name": "Alfred Hitchcock", "slug": "alfred-hitchcock"}}, {"date": "2012-02-14", "venue": "Encore HD", "sequence": 73, "movie": {"imdb_id": "tt0047396", "title": "Rear Window", "year": 1954, "decade": "1950s", "slug": null}, "person": {"imdb_id": "nm0000033", "full_name": "Alfred Hitchcock", "slug": "alfred-hitchcock"}}, {"date": "2012-04-08", "venue": "TCM HD", "sequence": 149, "movie": {"imdb_id": "tt0045897", "title": "I Confess", "year": 1953, "decade": "1950s", "slug": null}, "person": {"imdb_id": "nm0000033", "full_name": "Alfred Hitchcock", "slug": "alfred-hitchcock"}}, {"date": "2012-06-10", "venue": "TCM HD", "sequence": 182, "movie": {"imdb_id": "tt0032484", "title": "Foreign Correspondent", "year": 1940, "decade": "1940s", "slug": null}, "person": {"imdb_id": "nm0000033", "full_name": "Alfred Hitchcock", "slug": "alfred-hitchcock"}}, {"date": "2012-06-12", "venue": "TCM HD", "sequence": 184, "movie": {"imdb_id": "tt0042004", "title": "Under Capricorn", "year": 1949, "decade": "1940s", "slug": null}, "person": {"imdb_id": "nm0000033", "full_name": "Alfred Hitchcock", "slug": "alfred-hitchcock"}}, {"date": "2012-07-08", "venue": "AFI Silver", "sequence": 198, "movie": {"imdb_id": "tt0052357", "title": "Vertigo", "year": 1958, "decade": "1950s", "slug": null}, "person": {"imdb_id": "nm0000033", "full_name": "Alfred Hitchcock", "slug": "alfred-hitchcock"}}, {"date": "2014-10-23", "venue": "Angelika Film Center Mosaic", "sequence": 438, "movie": {"imdb_id": "tt0047396", "title": "Rear Window", "year": 1954, "decade": "1950s", "slug": null}, "person": {"imdb_id": "nm0000033", "full_name": "Alfred Hitchcock", "slug": "alfred-hitchcock"}}, {"date": "2018-04-04", "venue": "TCM", "sequence": 660, "movie": {"imdb_id": "tt0029811", "title": "Young and Innocent", "year": 1937, "decade": "1930s", "slug": null}, "person": {"imdb_id": "nm0000033", "full_name": "Alfred Hitchcock", "slug": "alfred-hitchcock"}}, {"date": "2020-07-10", "venue": "Kanopy", "sequence": 837, "movie": {"imdb_id": "tt0019702", "title": "Blackmail", "year": 1929, "decade": "1920s", "slug": "blackmail-1929"}, "person": {"imdb_id": "nm0000033", "full_name": "Alfred Hitchcock", "slug": "alfred-hitchcock"}}, {"date": "2020-09-28", "venue": "iTunes", "sequence": 875, "movie": {"imdb_id": "tt0021165", "title": "Murder!", "year": 1930, "decade": "1930s", "slug": "murder-1930"}, "person": {"imdb_id": "nm0000033", "full_name": "Alfred Hitchcock", "slug": "alfred-hitchcock"}}, {"date": "2020-11-02", "venue": "DVD", "sequence": 908, "movie": {"imdb_id": "tt0021015", "title": "Juno and the Paycock", "year": 1930, "decade": "1930s", "slug": "juno-and-the-paycock-1930"}, "person": {"imdb_id": "nm0000033", "full_name": "Alfred Hitchcock", "slug": "alfred-hitchcock"}}, {"date": "2021-01-09", "venue": "Blu-ray", "sequence": 978, "movie": {"imdb_id": "tt0022395", "title": "The Skin Game", "year": 1931, "decade": "1930s", "slug": "the-skin-game-1931"}, "person": {"imdb_id": "nm0000033", "full_name": "Alfred Hitchcock", "slug": "alfred-hitchcock"}}], "viewing_count": 12}, {"imdb_id": "nm0002086", "full_name": "Lucio Fulci", "slug": "lucio-fulci", "movie_count": 11, "viewings": [{"date": "2012-05-04", "venue": "Blu-ray", "sequence": 175, "movie": {"imdb_id": "tt0082966", "title": "The House by the Cemetery", "year": 1981, "decade": "1980s", "slug": null}, "person": {"imdb_id": "nm0002086", "full_name": "Lucio Fulci", "slug": "lucio-fulci"}}, {"date": "2012-06-14", "venue": "Blu-ray", "sequence": 191, "movie": {"imdb_id": "tt0081318", "title": "City of the Living Dead", "year": 1980, "decade": "1980s", "slug": null}, "person": {"imdb_id": "nm0002086", "full_name": "Lucio Fulci", "slug": "lucio-fulci"}}, {"date": "2015-06-23", "venue": "Alamo Drafthouse Cinema - Winchester", "sequence": 503, "movie": {"imdb_id": "tt0082307", "title": "The Beyond", "year": 1981, "decade": "1980s", "slug": null}, "person": {"imdb_id": "nm0002086", "full_name": "Lucio Fulci", "slug": "lucio-fulci"}}, {"date": "2015-11-05", "venue": "AFI Silver", "sequence": 532, "movie": {"imdb_id": "tt0082307", "title": "The Beyond", "year": 1981, "decade": "1980s", "slug": null}, "person": {"imdb_id": "nm0002086", "full_name": "Lucio Fulci", "slug": "lucio-fulci"}}, {"date": "2016-06-22", "venue": "Alamo Drafthouse Cinema - One Loudoun", "sequence": 552, "movie": {"imdb_id": "tt0099637", "title": "A Cat in the Brain", "year": 1990, "decade": "1990s", "slug": null}, "person": {"imdb_id": "nm0002086", "full_name": "Lucio Fulci", "slug": "lucio-fulci"}}, {"date": "2018-01-20", "venue": "Alamo Drafthouse Cinema - One Loudoun", "sequence": 633, "movie": {"imdb_id": "tt0096511", "title": "Zombie 3", "year": 1988, "decade": "1980s", "slug": null}, "person": {"imdb_id": "nm0002086", "full_name": "Lucio Fulci", "slug": "lucio-fulci"}}, {"date": "2018-10-13", "venue": "Alamo Drafthouse Cinema - One Loudoun", "sequence": 710, "movie": {"imdb_id": "tt0080057", "title": "Zombie", "year": 1979, "decade": "1970s", "slug": null}, "person": {"imdb_id": "nm0002086", "full_name": "Lucio Fulci", "slug": "lucio-fulci"}}, {"date": "2020-09-21", "venue": "DVD", "sequence": 872, "movie": {"imdb_id": "tt0061074", "title": "The Brute and the Beast", "year": 1966, "decade": "1960s", "slug": "the-brute-and-the-beast-1966"}, "person": {"imdb_id": "nm0002086", "full_name": "Lucio Fulci", "slug": "lucio-fulci"}}, {"date": "2020-09-24", "venue": "Blu-ray", "sequence": 873, "movie": {"imdb_id": "tt0065148", "title": "One on Top of the Other", "year": 1969, "decade": "1960s", "slug": "one-on-top-of-the-other-1969"}, "person": {"imdb_id": "nm0002086", "full_name": "Lucio Fulci", "slug": "lucio-fulci"}}, {"date": "2020-10-22", "venue": "Blu-ray", "sequence": 895, "movie": {"imdb_id": "tt0064073", "title": "The Conspiracy of Torture", "year": 1969, "decade": "1960s", "slug": "the-conspiracy-of-torture-1969"}, "person": {"imdb_id": "nm0002086", "full_name": "Lucio Fulci", "slug": "lucio-fulci"}}, {"date": "2020-10-23", "venue": "Blu-ray", "sequence": 896, "movie": {"imdb_id": "tt0067361", "title": "A Lizard in a Woman's Skin", "year": 1971, "decade": "1970s", "slug": "a-lizard-in-a-womans-skin-1971"}, "person": {"imdb_id": "nm0002086", "full_name": "Lucio Fulci", "slug": "lucio-fulci"}}, {"date": "2020-10-27", "venue": "iTunes", "sequence": 900, "movie": {"imdb_id": "tt0069019", "title": "Don't Torture a Duckling", "year": 1972, "decade": "1970s", "slug": "dont-torture-a-duckling-1972"}, "person": {"imdb_id": "nm0002086", "full_name": "Lucio Fulci", "slug": "lucio-fulci"}}], "viewing_count": 12}, {"imdb_id": "nm0102908", "full_name": "Robert N. Bradbury", "slug": null, "movie_count": 10, "viewings": [{"date": "2012-02-25", "venue": "Netflix", "sequence": 91, "movie": {"imdb_id": "tt0024500", "title": "Riders of Destiny", "year": 1933, "decade": "1930s", "slug": null}, "person": {"imdb_id": "nm0102908", "full_name": "Robert N. Bradbury", "slug": null}}, {"date": "2012-02-26", "venue": "Netflix", "sequence": 93, "movie": {"imdb_id": "tt0025373", "title": "The Lawless Frontier", "year": 1934, "decade": "1930s", "slug": null}, "person": {"imdb_id": "nm0102908", "full_name": "Robert N. Bradbury", "slug": null}}, {"date": "2012-02-27", "venue": "Netflix", "sequence": 95, "movie": {"imdb_id": "tt0025455", "title": "The Man from Utah", "year": 1934, "decade": "1930s", "slug": null}, "person": {"imdb_id": "nm0102908", "full_name": "Robert N. Bradbury", "slug": null}}, {"date": "2012-02-27", "venue": "Netflix", "sequence": 96, "movie": {"imdb_id": "tt0025969", "title": "West of the Divide", "year": 1934, "decade": "1930s", "slug": null}, "person": {"imdb_id": "nm0102908", "full_name": "Robert N. Bradbury", "slug": null}}, {"date": "2012-02-28", "venue": "Netflix", "sequence": 100, "movie": {"imdb_id": "tt0025830", "title": "The Star Packer", "year": 1934, "decade": "1930s", "slug": null}, "person": {"imdb_id": "nm0102908", "full_name": "Robert N. Bradbury", "slug": null}}, {"date": "2012-02-28", "venue": "Netflix", "sequence": 101, "movie": {"imdb_id": "tt0025903", "title": "The Trail Beyond", "year": 1934, "decade": "1930s", "slug": null}, "person": {"imdb_id": "nm0102908", "full_name": "Robert N. Bradbury", "slug": null}}, {"date": "2012-02-28", "venue": "Netflix", "sequence": 102, "movie": {"imdb_id": "tt0025440", "title": "The Lucky Texan", "year": 1934, "decade": "1930s", "slug": null}, "person": {"imdb_id": "nm0102908", "full_name": "Robert N. Bradbury", "slug": null}}, {"date": "2012-02-28", "venue": "Netflix", "sequence": 103, "movie": {"imdb_id": "tt0027087", "title": "Texas Terror", "year": 1935, "decade": "1930s", "slug": null}, "person": {"imdb_id": "nm0102908", "full_name": "Robert N. Bradbury", "slug": null}}, {"date": "2012-02-28", "venue": "Netflix", "sequence": 106, "movie": {"imdb_id": "tt0024902", "title": "Blue Steel", "year": 1934, "decade": "1930s", "slug": null}, "person": {"imdb_id": "nm0102908", "full_name": "Robert N. Bradbury", "slug": null}}, {"date": "2012-02-28", "venue": "Netflix", "sequence": 107, "movie": {"imdb_id": "tt0026267", "title": "The Dawn Rider", "year": 1935, "decade": "1930s", "slug": null}, "person": {"imdb_id": "nm0102908", "full_name": "Robert N. Bradbury", "slug": null}}, {"date": "2016-09-17", "venue": "Amazon", "sequence": 560, "movie": {"imdb_id": "tt0024500", "title": "Riders of Destiny", "year": 1933, "decade": "1930s", "slug": null}, "person": {"imdb_id": "nm0102908", "full_name": "Robert N. Bradbury", "slug": null}}], "viewing_count": 11}, {"imdb_id": "nm0000783", "full_name": "Dario Argento", "slug": null, "movie_count": 8, "viewings": [{"date": "2013-10-29", "venue": "Netflix", "sequence": 329, "movie": {"imdb_id": "tt1107816", "title": "Giallo", "year": 2009, "decade": "2000s", "slug": null}, "person": {"imdb_id": "nm0000783", "full_name": "Dario Argento", "slug": null}}, {"date": "2014-02-01", "venue": "Netflix", "sequence": 368, "movie": {"imdb_id": "tt1852770", "title": "Dracula 3D", "year": 2012, "decade": "2010s", "slug": null}, "person": {"imdb_id": "nm0000783", "full_name": "Dario Argento", "slug": null}}, {"date": "2014-05-17", "venue": "Blu-ray", "sequence": 388, "movie": {"imdb_id": "tt0065143", "title": "The Bird with the Crystal Plumage", "year": 1970, "decade": "1970s", "slug": null}, "person": {"imdb_id": "nm0000783", "full_name": "Dario Argento", "slug": null}}, {"date": "2014-05-31", "venue": "Blu-ray", "sequence": 393, "movie": {"imdb_id": "tt0080923", "title": "Inferno", "year": 1980, "decade": "1980s", "slug": null}, "person": {"imdb_id": "nm0000783", "full_name": "Dario Argento", "slug": null}}, {"date": "2015-08-08", "venue": "Shudder", "sequence": 511, "movie": {"imdb_id": "tt0100827", "title": "Two Evil Eyes", "year": 1990, "decade": "1990s", "slug": null}, "person": {"imdb_id": "nm0000783", "full_name": "Dario Argento", "slug": null}}, {"date": "2017-01-31", "venue": "Blu-ray", "sequence": 582, "movie": {"imdb_id": "tt0065143", "title": "The Bird with the Crystal Plumage", "year": 1970, "decade": "1970s", "slug": null}, "person": {"imdb_id": "nm0000783", "full_name": "Dario Argento", "slug": null}}, {"date": "2017-10-21", "venue": "Alamo Drafthouse Cinema - One Loudoun", "sequence": 613, "movie": {"imdb_id": "tt0076786", "title": "Suspiria", "year": 1977, "decade": "1970s", "slug": null}, "person": {"imdb_id": "nm0000783", "full_name": "Dario Argento", "slug": null}}, {"date": "2018-03-10", "venue": "Shudder", "sequence": 644, "movie": {"imdb_id": "tt0084777", "title": "Tenebrae", "year": 1982, "decade": "1980s", "slug": null}, "person": {"imdb_id": "nm0000783", "full_name": "Dario Argento", "slug": null}}, {"date": "2018-03-23", "venue": "AFI Silver", "sequence": 649, "movie": {"imdb_id": "tt0065143", "title": "The Bird with the Crystal Plumage", "year": 1970, "decade": "1970s", "slug": null}, "person": {"imdb_id": "nm0000783", "full_name": "Dario Argento", "slug": null}}, {"date": "2018-10-27", "venue": "Alamo Drafthouse Cinema - Woodbridge", "sequence": 715, "movie": {"imdb_id": "tt0073582", "title": "Deep Red", "year": 1975, "decade": "1970s", "slug": null}, "person": {"imdb_id": "nm0000783", "full_name": "Dario Argento", "slug": null}}], "viewing_count": 10}, {"imdb_id": "nm0002031", "full_name": "Michael Curtiz", "slug": null, "movie_count": 8, "viewings": [{"date": "2012-01-21", "venue": "TCM HD", "sequence": 27, "movie": {"imdb_id": "tt0025346", "title": "The Key", "year": 1934, "decade": "1930s", "slug": null}, "person": {"imdb_id": "nm0002031", "full_name": "Michael Curtiz", "slug": null}}, {"date": "2012-01-25", "venue": "TCM HD", "sequence": 29, "movie": {"imdb_id": "tt0029080", "title": "Kid Galahad", "year": 1937, "decade": "1930s", "slug": null}, "person": {"imdb_id": "nm0002031", "full_name": "Michael Curtiz", "slug": null}}, {"date": "2012-01-28", "venue": "TCM HD", "sequence": 44, "movie": {"imdb_id": "tt0037166", "title": "Passage to Marseille", "year": 1944, "decade": "1940s", "slug": null}, "person": {"imdb_id": "nm0002031", "full_name": "Michael Curtiz", "slug": null}}, {"date": "2012-02-15", "venue": "TCM HD", "sequence": 74, "movie": {"imdb_id": "tt0039566", "title": "Life with Father", "year": 1947, "decade": "1940s", "slug": null}, "person": {"imdb_id": "nm0002031", "full_name": "Michael Curtiz", "slug": null}}, {"date": "2012-03-18", "venue": "TCM HD", "sequence": 118, "movie": {"imdb_id": "tt0033226", "title": "Virginia City", "year": 1940, "decade": "1940s", "slug": null}, "person": {"imdb_id": "nm0002031", "full_name": "Michael Curtiz", "slug": null}}, {"date": "2012-06-14", "venue": "TCM HD", "sequence": 188, "movie": {"imdb_id": "tt0027367", "title": "Black Legion", "year": 1937, "decade": "1930s", "slug": null}, "person": {"imdb_id": "nm0002031", "full_name": "Michael Curtiz", "slug": null}}, {"date": "2016-02-28", "venue": "Blu-ray", "sequence": 540, "movie": {"imdb_id": "tt0034583", "title": "Casablanca", "year": 1942, "decade": "1940s", "slug": null}, "person": {"imdb_id": "nm0002031", "full_name": "Michael Curtiz", "slug": null}}, {"date": "2018-03-25", "venue": "TCM", "sequence": 654, "movie": {"imdb_id": "tt0029080", "title": "Kid Galahad", "year": 1937, "decade": "1930s", "slug": null}, "person": {"imdb_id": "nm0002031", "full_name": "Michael Curtiz", "slug": null}}, {"date": "2018-08-05", "venue": "TCM", "sequence": 695, "movie": {"imdb_id": "tt0024471", "title": "Private Detective 62", "year": 1933, "decade": "1930s", "slug": null}, "person": {"imdb_id": "nm0002031", "full_name": "Michael Curtiz", "slug": null}}], "viewing_count": 9}, {"imdb_id": "nm0001603", "full_name": "Sam Peckinpah", "slug": null, "movie_count": 7, "viewings": [{"date": "2012-01-28", "venue": "Blu-ray", "sequence": 47, "movie": {"imdb_id": "tt0067800", "title": "Straw Dogs", "year": 1971, "decade": "1970s", "slug": null}, "person": {"imdb_id": "nm0001603", "full_name": "Sam Peckinpah", "slug": null}}, {"date": "2012-04-08", "venue": "TCM HD", "sequence": 151, "movie": {"imdb_id": "tt0056412", "title": "Ride the High Country", "year": 1962, "decade": "1960s", "slug": null}, "person": {"imdb_id": "nm0001603", "full_name": "Sam Peckinpah", "slug": null}}, {"date": "2013-03-02", "venue": "TCM HD", "sequence": 287, "movie": {"imdb_id": "tt0054795", "title": "The Deadly Companions", "year": 1961, "decade": "1960s", "slug": null}, "person": {"imdb_id": "nm0001603", "full_name": "Sam Peckinpah", "slug": null}}, {"date": "2016-11-27", "venue": "Blu-ray", "sequence": 571, "movie": {"imdb_id": "tt0068638", "title": "The Getaway", "year": 1972, "decade": "1970s", "slug": null}, "person": {"imdb_id": "nm0001603", "full_name": "Sam Peckinpah", "slug": null}}, {"date": "2016-12-02", "venue": "Blu-ray", "sequence": 573, "movie": {"imdb_id": "tt0067800", "title": "Straw Dogs", "year": 1971, "decade": "1970s", "slug": null}, "person": {"imdb_id": "nm0001603", "full_name": "Sam Peckinpah", "slug": null}}, {"date": "2017-11-18", "venue": "HDNet", "sequence": 620, "movie": {"imdb_id": "tt0065446", "title": "The Ballad of Cable Hogue", "year": 1970, "decade": "1970s", "slug": null}, "person": {"imdb_id": "nm0001603", "full_name": "Sam Peckinpah", "slug": null}}, {"date": "2018-04-23", "venue": "HDNet", "sequence": 668, "movie": {"imdb_id": "tt0070518", "title": "Pat Garrett & Billy the Kid", "year": 1973, "decade": "1970s", "slug": null}, "person": {"imdb_id": "nm0001603", "full_name": "Sam Peckinpah", "slug": null}}, {"date": "2019-05-07", "venue": "Alamo Drafthouse Cinema - One Loudoun", "sequence": 749, "movie": {"imdb_id": "tt0065214", "title": "The Wild Bunch", "year": 1969, "decade": "1960s", "slug": null}, "person": {"imdb_id": "nm0001603", "full_name": "Sam Peckinpah", "slug": null}}], "viewing_count": 8}, {"imdb_id": "nm0000697", "full_name": "Billy Wilder", "slug": null, "movie_count": 6, "viewings": [{"date": "2012-01-28", "venue": "TCM HD", "sequence": 49, "movie": {"imdb_id": "tt0051201", "title": "Witness for the Prosecution", "year": 1957, "decade": "1950s", "slug": null}, "person": {"imdb_id": "nm0000697", "full_name": "Billy Wilder", "slug": null}}, {"date": "2012-11-01", "venue": "TCM HD", "sequence": 236, "movie": {"imdb_id": "tt0051003", "title": "The Spirit of St. Louis", "year": 1957, "decade": "1950s", "slug": null}, "person": {"imdb_id": "nm0000697", "full_name": "Billy Wilder", "slug": null}}, {"date": "2013-01-27", "venue": "Netflix", "sequence": 271, "movie": {"imdb_id": "tt0036775", "title": "Double Indemnity", "year": 1944, "decade": "1940s", "slug": null}, "person": {"imdb_id": "nm0000697", "full_name": "Billy Wilder", "slug": null}}, {"date": "2013-03-09", "venue": "Netflix", "sequence": 291, "movie": {"imdb_id": "tt0055256", "title": "One, Two, Three", "year": 1961, "decade": "1960s", "slug": null}, "person": {"imdb_id": "nm0000697", "full_name": "Billy Wilder", "slug": null}}, {"date": "2016-06-18", "venue": "Blu-ray", "sequence": 551, "movie": {"imdb_id": "tt0053291", "title": "Some Like It Hot", "year": 1959, "decade": "1950s", "slug": null}, "person": {"imdb_id": "nm0000697", "full_name": "Billy Wilder", "slug": null}}, {"date": "2019-04-17", "venue": "Alamo Drafthouse Cinema - One Loudoun", "sequence": 747, "movie": {"imdb_id": "tt0053291", "title": "Some Like It Hot", "year": 1959, "decade": "1950s", "slug": null}, "person": {"imdb_id": "nm0000697", "full_name": "Billy Wilder", "slug": null}}, {"date": "2020-03-11", "venue": "Alamo Drafthouse Cinema - One Loudoun", "sequence": 820, "movie": {"imdb_id": "tt0043338", "title": "Ace in the Hole", "year": 1951, "decade": "1950s", "slug": null}, "person": {"imdb_id": "nm0000697", "full_name": "Billy Wilder", "slug": null}}], "viewing_count": 7}, {"imdb_id": "nm0000343", "full_name": "David Cronenberg", "slug": "david-cronenberg", "movie_count": 5, "viewings": [{"date": "2012-01-30", "venue": "Netflix", "sequence": 54, "movie": {"imdb_id": "tt0086541", "title": "Videodrome", "year": 1983, "decade": "1980s", "slug": null}, "person": {"imdb_id": "nm0000343", "full_name": "David Cronenberg", "slug": "david-cronenberg"}}, {"date": "2013-12-21", "venue": "Netflix", "sequence": 352, "movie": {"imdb_id": "tt0120907", "title": "eXistenZ", "year": 1999, "decade": "1990s", "slug": null}, "person": {"imdb_id": "nm0000343", "full_name": "David Cronenberg", "slug": "david-cronenberg"}}, {"date": "2014-11-01", "venue": "Blu-ray", "sequence": 443, "movie": {"imdb_id": "tt0086541", "title": "Videodrome", "year": 1983, "decade": "1980s", "slug": null}, "person": {"imdb_id": "nm0000343", "full_name": "David Cronenberg", "slug": "david-cronenberg"}}, {"date": "2015-10-24", "venue": "Blu-ray", "sequence": 528, "movie": {"imdb_id": "tt0081455", "title": "Scanners", "year": 1981, "decade": "1980s", "slug": null}, "person": {"imdb_id": "nm0000343", "full_name": "David Cronenberg", "slug": "david-cronenberg"}}, {"date": "2018-10-01", "venue": "Alamo Drafthouse Cinema - One Loudoun", "sequence": 704, "movie": {"imdb_id": "tt0086541", "title": "Videodrome", "year": 1983, "decade": "1980s", "slug": null}, "person": {"imdb_id": "nm0000343", "full_name": "David Cronenberg", "slug": "david-cronenberg"}}, {"date": "2020-12-26", "venue": "Criterion Channel", "sequence": 963, "movie": {"imdb_id": "tt0065036", "title": "Stereo (Tile 3B of a CAEE Educational Mosaic)", "year": 1969, "decade": "1960s", "slug": "stereo-tile-3b-of-a-caee-educational-mosaic-1969"}, "person": {"imdb_id": "nm0000343", "full_name": "David Cronenberg", "slug": "david-cronenberg"}}, {"date": "2021-01-03", "venue": "Criterion Channel", "sequence": 971, "movie": {"imdb_id": "tt0065591", "title": "Crimes of the Future", "year": 1970, "decade": "1970s", "slug": "crimes-of-the-future-1970"}, "person": {"imdb_id": "nm0000343", "full_name": "David Cronenberg", "slug": "david-cronenberg"}}], "viewing_count": 7}, {"imdb_id": "nm1206844", "full_name": "Drew Goddard", "slug": null, "movie_count": 2, "viewings": [{"date": "2012-04-12", "venue": "AMC Tysons Corner 16", "sequence": 158, "movie": {"imdb_id": "tt1259521", "title": "The Cabin in the Woods", "year": 2011, "decade": "2010s", "slug": "the-cabin-in-the-woods-2011"}, "person": {"imdb_id": "nm1206844", "full_name": "Drew Goddard", "slug": null}}, {"date": "2013-02-16", "venue": "Blu-ray", "sequence": 280, "movie": {"imdb_id": "tt1259521", "title": "The Cabin in the Woods", "year": 2011, "decade": "2010s", "slug": "the-cabin-in-the-woods-2011"}, "person": {"imdb_id": "nm1206844", "full_name": "Drew Goddard", "slug": null}}, {"date": "2015-10-31", "venue": "Blu-ray", "sequence": 529, "movie": {"imdb_id": "tt1259521", "title": "The Cabin in the Woods", "year": 2011, "decade": "2010s", "slug": "the-cabin-in-the-woods-2011"}, "person": {"imdb_id": "nm1206844", "full_name": "Drew Goddard", "slug": null}}, {"date": "2016-10-26", "venue": "Alamo Drafthouse Cinema - One Loudoun", "sequence": 565, "movie": {"imdb_id": "tt1259521", "title": "The Cabin in the Woods", "year": 2011, "decade": "2010s", "slug": "the-cabin-in-the-woods-2011"}, "person": {"imdb_id": "nm1206844", "full_name": "Drew Goddard", "slug": null}}, {"date": "2018-10-21", "venue": "Alamo Drafthouse Cinema - One Loudoun", "sequence": 711, "movie": {"imdb_id": "tt6628394", "title": "Bad Times at the El Royale", "year": 2018, "decade": "2010s", "slug": null}, "person": {"imdb_id": "nm1206844", "full_name": "Drew Goddard", "slug": null}}, {"date": "2020-02-08", "venue": "4k UHD Blu-ray", "sequence": 814, "movie": {"imdb_id": "tt1259521", "title": "The Cabin in the Woods", "year": 2011, "decade": "2010s", "slug": "the-cabin-in-the-woods-2011"}, "person": {"imdb_id": "nm1206844", "full_name": "Drew Goddard", "slug": null}}, {"date": "2020-12-22", "venue": "4k UHD Blu-ray", "sequence": 955, "movie": {"imdb_id": "tt1259521", "title": "The Cabin in the Woods", "year": 2011, "decade": "2010s", "slug": "the-cabin-in-the-woods-2011"}, "person": {"imdb_id": "nm1206844", "full_name": "Drew Goddard", "slug": null}}], "viewing_count": 7}, {"imdb_id": "nm0000878", "full_name": "Mario Bava", "slug": "mario-bava", "movie_count": 7, "viewings": [{"date": "2012-10-20", "venue": "Netflix", "sequence": 229, "movie": {"imdb_id": "tt0067656", "title": "A Bay of Blood", "year": 1971, "decade": "1970s", "slug": null}, "person": {"imdb_id": "nm0000878", "full_name": "Mario Bava", "slug": "mario-bava"}}, {"date": "2012-10-27", "venue": "Netflix", "sequence": 232, "movie": {"imdb_id": "tt0069048", "title": "Baron Blood", "year": 1972, "decade": "1970s", "slug": null}, "person": {"imdb_id": "nm0000878", "full_name": "Mario Bava", "slug": "mario-bava"}}, {"date": "2012-11-01", "venue": "Netflix", "sequence": 239, "movie": {"imdb_id": "tt0068863", "title": "Lisa and the Devil", "year": 1973, "decade": "1970s", "slug": null}, "person": {"imdb_id": "nm0000878", "full_name": "Mario Bava", "slug": "mario-bava"}}, {"date": "2015-08-29", "venue": "Shudder", "sequence": 519, "movie": {"imdb_id": "tt0057078", "title": "The Whip and the Body", "year": 1963, "decade": "1960s", "slug": null}, "person": {"imdb_id": "nm0000878", "full_name": "Mario Bava", "slug": "mario-bava"}}, {"date": "2018-01-22", "venue": "Alamo Drafthouse Cinema - One Loudoun", "sequence": 634, "movie": {"imdb_id": "tt0058567", "title": "Blood and Black Lace", "year": 1964, "decade": "1960s", "slug": null}, "person": {"imdb_id": "nm0000878", "full_name": "Mario Bava", "slug": "mario-bava"}}, {"date": "2020-12-10", "venue": "Blu-ray", "sequence": 938, "movie": {"imdb_id": "tt0049429", "title": "Lust of the Vampire", "year": 1957, "decade": "1950s", "slug": "lust-of-the-vampire-1957"}, "person": {"imdb_id": "nm0000878", "full_name": "Mario Bava", "slug": "mario-bava"}}, {"date": "2021-01-08", "venue": "DVD", "sequence": 976, "movie": {"imdb_id": "tt0051951", "title": "The Day the Sky Exploded", "year": 1958, "decade": "1950s", "slug": "the-day-the-sky-exploded-1958"}, "person": {"imdb_id": "nm0000878", "full_name": "Mario Bava", "slug": "mario-bava"}}], "viewing_count": 7}, {"imdb_id": "nm0276169", "full_name": "Tom Holland", "slug": null, "movie_count": 1, "viewings": [{"date": "2012-01-28", "venue": "Blu-ray", "sequence": 48, "movie": {"imdb_id": "tt0089175", "title": "Fright Night", "year": 1985, "decade": "1980s", "slug": "fright-night-1985"}, "person": {"imdb_id": "nm0276169", "full_name": "Tom Holland", "slug": null}}, {"date": "2012-07-07", "venue": "AFI Silver", "sequence": 197, "movie": {"imdb_id": "tt0089175", "title": "Fright Night", "year": 1985, "decade": "1980s", "slug": "fright-night-1985"}, "person": {"imdb_id": "nm0276169", "full_name": "Tom Holland", "slug": null}}, {"date": "2012-07-08", "venue": "AFI Silver", "sequence": 199, "movie": {"imdb_id": "tt0089175", "title": "Fright Night", "year": 1985, "decade": "1980s", "slug": "fright-night-1985"}, "person": {"imdb_id": "nm0276169", "full_name": "Tom Holland", "slug": null}}, {"date": "2012-07-30", "venue": "The Black Cat", "sequence": 210, "movie": {"imdb_id": "tt0089175", "title": "Fright Night", "year": 1985, "decade": "1980s", "slug": "fright-night-1985"}, "person": {"imdb_id": "nm0276169", "full_name": "Tom Holland", "slug": null}}, {"date": "2015-08-22", "venue": "Alamo Drafthouse Cinema - One Loudoun", "sequence": 518, "movie": {"imdb_id": "tt0089175", "title": "Fright Night", "year": 1985, "decade": "1980s", "slug": "fright-night-1985"}, "person": {"imdb_id": "nm0276169", "full_name": "Tom Holland", "slug": null}}, {"date": "2020-10-31", "venue": "Blu-ray", "sequence": 906, "movie": {"imdb_id": "tt0089175", "title": "Fright Night", "year": 1985, "decade": "1980s", "slug": "fright-night-1985"}, "person": {"imdb_id": "nm0276169", "full_name": "Tom Holland", "slug": null}}], "viewing_count": 6}, {"imdb_id": "nm0001379", "full_name": "John Huston", "slug": null, "movie_count": 6, "viewings": [{"date": "2012-02-04", "venue": "TCM HD", "sequence": 61, "movie": {"imdb_id": "tt0040506", "title": "Key Largo", "year": 1948, "decade": "1940s", "slug": null}, "person": {"imdb_id": "nm0001379", "full_name": "John Huston", "slug": null}}, {"date": "2012-02-05", "venue": "TCM HD", "sequence": 65, "movie": {"imdb_id": "tt0088322", "title": "Under the Volcano", "year": 1984, "decade": "1980s", "slug": null}, "person": {"imdb_id": "nm0001379", "full_name": "John Huston", "slug": null}}, {"date": "2012-02-05", "venue": "TCM HD", "sequence": 66, "movie": {"imdb_id": "tt0058404", "title": "The Night of the Iguana", "year": 1964, "decade": "1960s", "slug": null}, "person": {"imdb_id": "nm0001379", "full_name": "John Huston", "slug": null}}, {"date": "2012-03-10", "venue": "Landmark E Street Cinema", "sequence": 111, "movie": {"imdb_id": "tt0033870", "title": "The Maltese Falcon", "year": 1941, "decade": "1940s", "slug": null}, "person": {"imdb_id": "nm0001379", "full_name": "John Huston", "slug": null}}, {"date": "2012-04-01", "venue": "TCM HD", "sequence": 142, "movie": {"imdb_id": "tt0042208", "title": "The Asphalt Jungle", "year": 1950, "decade": "1950s", "slug": null}, "person": {"imdb_id": "nm0001379", "full_name": "John Huston", "slug": null}}, {"date": "2018-04-19", "venue": "Amazon", "sequence": 666, "movie": {"imdb_id": "tt0046414", "title": "Beat the Devil", "year": 1953, "decade": "1950s", "slug": null}, "person": {"imdb_id": "nm0001379", "full_name": "John Huston", "slug": null}}], "viewing_count": 6}, {"imdb_id": "nm0000233", "full_name": "Quentin Tarantino", "slug": null, "movie_count": 5, "viewings": [{"date": "2013-01-03", "venue": "AMC Tysons Corner 16", "sequence": 258, "movie": {"imdb_id": "tt1853728", "title": "Django Unchained", "year": 2012, "decade": "2010s", "slug": null}, "person": {"imdb_id": "nm0000233", "full_name": "Quentin Tarantino", "slug": null}}, {"date": "2014-02-16", "venue": "Blu-ray", "sequence": 372, "movie": {"imdb_id": "tt0266697", "title": "Kill Bill: Vol. 1", "year": 2003, "decade": "2000s", "slug": null}, "person": {"imdb_id": "nm0000233", "full_name": "Quentin Tarantino", "slug": null}}, {"date": "2014-03-29", "venue": "Blu-ray", "sequence": 378, "movie": {"imdb_id": "tt0378194", "title": "Kill Bill: Vol. 2", "year": 2004, "decade": "2000s", "slug": null}, "person": {"imdb_id": "nm0000233", "full_name": "Quentin Tarantino", "slug": null}}, {"date": "2015-12-29", "venue": "AFI Silver", "sequence": 537, "movie": {"imdb_id": "tt3460252", "title": "The Hateful Eight", "year": 2015, "decade": "2010s", "slug": null}, "person": {"imdb_id": "nm0000233", "full_name": "Quentin Tarantino", "slug": null}}, {"date": "2019-08-22", "venue": "AFI Silver", "sequence": 773, "movie": {"imdb_id": "tt7131622", "title": "Once Upon a Time... In Hollywood", "year": 2019, "decade": "2010s", "slug": null}, "person": {"imdb_id": "nm0000233", "full_name": "Quentin Tarantino", "slug": null}}, {"date": "2019-09-09", "venue": "Alamo Drafthouse Cinema - One Loudoun", "sequence": 779, "movie": {"imdb_id": "tt7131622", "title": "Once Upon a Time... In Hollywood", "year": 2019, "decade": "2010s", "slug": null}, "person": {"imdb_id": "nm0000233", "full_name": "Quentin Tarantino", "slug": null}}], "viewing_count": 6}, {"imdb_id": "nm0591171", "full_name": "Steve Miner", "slug": null, "movie_count": 4, "viewings": [{"date": "2013-01-05", "venue": "Netflix", "sequence": 259, "movie": {"imdb_id": "tt0098622", "title": "Warlock", "year": 1989, "decade": "1980s", "slug": null}, "person": {"imdb_id": "nm0591171", "full_name": "Steve Miner", "slug": null}}, {"date": "2013-09-21", "venue": "Blu-ray", "sequence": 317, "movie": {"imdb_id": "tt0082418", "title": "Friday the 13th Part 2", "year": 1981, "decade": "1980s", "slug": "friday-the-13th-part-2-1981"}, "person": {"imdb_id": "nm0591171", "full_name": "Steve Miner", "slug": null}}, {"date": "2013-09-27", "venue": "Blu-ray", "sequence": 318, "movie": {"imdb_id": "tt0083972", "title": "Friday the 13th Part III", "year": 1982, "decade": "1980s", "slug": null}, "person": {"imdb_id": "nm0591171", "full_name": "Steve Miner", "slug": null}}, {"date": "2019-02-09", "venue": "Vudu", "sequence": 735, "movie": {"imdb_id": "tt0120694", "title": "Halloween H20: 20 Years Later", "year": 1998, "decade": "1990s", "slug": null}, "person": {"imdb_id": "nm0591171", "full_name": "Steve Miner", "slug": null}}, {"date": "2019-09-13", "venue": "Alamo Drafthouse Cinema - One Loudoun", "sequence": 781, "movie": {"imdb_id": "tt0082418", "title": "Friday the 13th Part 2", "year": 1981, "decade": "1980s", "slug": "friday-the-13th-part-2-1981"}, "person": {"imdb_id": "nm0591171", "full_name": "Steve Miner", "slug": null}}, {"date": "2020-11-13", "venue": "Blu-ray", "sequence": 916, "movie": {"imdb_id": "tt0082418", "title": "Friday the 13th Part 2", "year": 1981, "decade": "1980s", "slug": "friday-the-13th-part-2-1981"}, "person": {"imdb_id": "nm0591171", "full_name": "Steve Miner", "slug": null}}], "viewing_count": 6}]}