{
  "name": "Anthony Shaffer",
  "slug": "anthony-shaffer",
  "director": {
    "titles": [],
    "reviewCount": 0,
    "watchlistCount": 0
  },
  "writer": {
    "titles": [
      {
        "imdbId": "tt0066961",
        "title": "Cry of the Penguins",
        "year": "1971",
        "slug": null,
        "grade": null,
        "sortTitle": "Cry of the Penguins (1971)",
        "gradeValue": null,
        "releaseSequence": "1971-12-30tt0066961",
        "reviewDate": null,
        "viewingSequence": null
      },
      {
        "imdbId": "tt0068611",
        "title": "Frenzy",
        "year": "1972",
        "slug": null,
        "grade": null,
        "sortTitle": "Frenzy (1972)",
        "gradeValue": null,
        "releaseSequence": "1972-05-19tt0068611",
        "reviewDate": null,
        "viewingSequence": null
      },
      {
        "imdbId": "tt0069281",
        "title": "Sleuth",
        "year": "1972",
        "slug": null,
        "grade": null,
        "sortTitle": "Sleuth (1972)",
        "gradeValue": null,
        "releaseSequence": "1972-12-10tt0069281",
        "reviewDate": null,
        "viewingSequence": null
      },
      {
        "imdbId": "tt0070917",
        "title": "The Wicker Man",
        "year": "1973",
        "slug": null,
        "grade": null,
        "sortTitle": "Wicker Man (1973)",
        "gradeValue": null,
        "releaseSequence": "1973-12-06tt0070917",
        "reviewDate": null,
        "viewingSequence": null
      },
      {
        "imdbId": "tt0081975",
        "title": "Absolution",
        "year": "1978",
        "slug": null,
        "grade": null,
        "sortTitle": "Absolution (1978)",
        "gradeValue": null,
        "releaseSequence": "1978-12-01tt0081975",
        "reviewDate": null,
        "viewingSequence": null
      },
      {
        "imdbId": "tt0077413",
        "title": "Death on the Nile",
        "year": "1978",
        "slug": null,
        "grade": null,
        "sortTitle": "Death on the Nile (1978)",
        "gradeValue": null,
        "releaseSequence": "1978-??-??tt0077413",
        "reviewDate": null,
        "viewingSequence": null
      },
      {
        "imdbId": "tt0083908",
        "title": "Evil Under the Sun",
        "year": "1982",
        "slug": null,
        "grade": null,
        "sortTitle": "Evil Under the Sun (1982)",
        "gradeValue": null,
        "releaseSequence": "1982-01-25tt0083908",
        "reviewDate": null,
        "viewingSequence": null
      },
      {
        "imdbId": "tt0094669",
        "title": "Appointment with Death",
        "year": "1988",
        "slug": null,
        "grade": null,
        "sortTitle": "Appointment with Death (1988)",
        "gradeValue": null,
        "releaseSequence": "1988-04-15tt0094669",
        "reviewDate": null,
        "viewingSequence": null
      },
      {
        "imdbId": "tt0108185",
        "title": "Sommersby",
        "year": "1993",
        "slug": null,
        "grade": null,
        "sortTitle": "Sommersby (1993)",
        "gradeValue": null,
        "releaseSequence": "1993-02-05tt0108185",
        "reviewDate": null,
        "viewingSequence": null
      },
      {
        "imdbId": "tt0450345",
        "title": "The Wicker Man",
        "year": "2006",
        "slug": null,
        "grade": null,
        "sortTitle": "Wicker Man (2006)",
        "gradeValue": null,
        "releaseSequence": "2006-08-31tt0450345",
        "reviewDate": null,
        "viewingSequence": null
      },
      {
        "imdbId": "tt0857265",
        "title": "Sleuth",
        "year": "2007",
        "slug": null,
        "grade": null,
        "sortTitle": "Sleuth (2007)",
        "gradeValue": null,
        "releaseSequence": "2007-08-30tt0857265",
        "reviewDate": null,
        "viewingSequence": null
      }
    ],
    "reviewCount": 0,
    "watchlistCount": 11
  },
  "performer": {
    "titles": [],
    "reviewCount": 0,
    "watchlistCount": 0
  }
}