{
  "name": "Neil LaBute",
  "slug": "neil-labute",
  "titles": [
    {
      "creditedAs": [
        "director",
        "writer"
      ],
      "imdbId": "tt0119361",
      "title": "In the Company of Men",
      "year": "1997",
      "slug": "in-the-company-of-men-1997",
      "grade": "A-",
      "sortTitle": "In the Company of Men (1997)",
      "gradeValue": 11,
      "releaseSequence": "1997-01-19tt0119361",
      "reviewDate": "2022-08-11",
      "viewingSequence": "2022-08-11-1317",
      "watchlistDirectorNames": [],
      "watchlistPerformerNames": [],
      "watchlistWriterNames": [],
      "collectionNames": []
    },
    {
      "creditedAs": [
        "director",
        "writer"
      ],
      "imdbId": "tt0119517",
      "title": "Your Friends and Neighbors",
      "year": "1998",
      "slug": null,
      "grade": null,
      "sortTitle": "Your Friends and Neighbors (1998)",
      "gradeValue": null,
      "releaseSequence": "1998-08-19tt0119517",
      "reviewDate": null,
      "viewingSequence": null,
      "watchlistDirectorNames": [],
      "watchlistPerformerNames": [],
      "watchlistWriterNames": [
        "Neil LaBute"
      ],
      "collectionNames": []
    },
    {
      "creditedAs": [
        "director",
        "writer"
      ],
      "imdbId": "tt0259210",
      "title": "Bash: Latter-Day Plays",
      "year": "2001",
      "slug": null,
      "grade": null,
      "sortTitle": "Bash: Latter-Day Plays (2001)",
      "gradeValue": null,
      "releaseSequence": "2001-08-28tt0259210",
      "reviewDate": null,
      "viewingSequence": null,
      "watchlistDirectorNames": [],
      "watchlistPerformerNames": [],
      "watchlistWriterNames": [
        "Neil LaBute"
      ],
      "collectionNames": []
    },
    {
      "creditedAs": [
        "director",
        "writer"
      ],
      "imdbId": "tt0256276",
      "title": "Possession",
      "year": "2002",
      "slug": null,
      "grade": null,
      "sortTitle": "Possession (2002)",
      "gradeValue": null,
      "releaseSequence": "2002-08-16tt0256276",
      "reviewDate": null,
      "viewingSequence": null,
      "watchlistDirectorNames": [],
      "watchlistPerformerNames": [],
      "watchlistWriterNames": [
        "Neil LaBute"
      ],
      "collectionNames": []
    },
    {
      "creditedAs": [
        "director",
        "writer"
      ],
      "imdbId": "tt0308878",
      "title": "The Shape of Things",
      "year": "2003",
      "slug": null,
      "grade": null,
      "sortTitle": "Shape of Things (2003)",
      "gradeValue": null,
      "releaseSequence": "2003-01-18tt0308878",
      "reviewDate": null,
      "viewingSequence": null,
      "watchlistDirectorNames": [],
      "watchlistPerformerNames": [],
      "watchlistWriterNames": [
        "Neil LaBute"
      ],
      "collectionNames": []
    },
    {
      "creditedAs": [
        "director",
        "writer"
      ],
      "imdbId": "tt0450345",
      "title": "The Wicker Man",
      "year": "2006",
      "slug": null,
      "grade": null,
      "sortTitle": "Wicker Man (2006)",
      "gradeValue": null,
      "releaseSequence": "2006-08-31tt0450345",
      "reviewDate": null,
      "viewingSequence": null,
      "watchlistDirectorNames": [],
      "watchlistPerformerNames": [],
      "watchlistWriterNames": [
        "Anthony Shaffer",
        "Neil LaBute"
      ],
      "collectionNames": []
    },
    {
      "creditedAs": [
        "writer"
      ],
      "imdbId": "tt2201221",
      "title": "Some Girl(S)",
      "year": "2013",
      "slug": null,
      "grade": null,
      "sortTitle": "Some Girl(S) (2013)",
      "gradeValue": null,
      "releaseSequence": "2013-03-09tt2201221",
      "reviewDate": null,
      "viewingSequence": null,
      "watchlistDirectorNames": [],
      "watchlistPerformerNames": [],
      "watchlistWriterNames": [
        "Neil LaBute"
      ],
      "collectionNames": []
    },
    {
      "creditedAs": [
        "director",
        "writer"
      ],
      "imdbId": "tt2231138",
      "title": "Some Velvet Morning",
      "year": "2013",
      "slug": null,
      "grade": null,
      "sortTitle": "Some Velvet Morning (2013)",
      "gradeValue": null,
      "releaseSequence": "2013-04-21tt2231138",
      "reviewDate": null,
      "viewingSequence": null,
      "watchlistDirectorNames": [],
      "watchlistPerformerNames": [],
      "watchlistWriterNames": [
        "Neil LaBute"
      ],
      "collectionNames": []
    },
    {
      "creditedAs": [
        "writer"
      ],
      "imdbId": "tt3831696",
      "title": "My America",
      "year": "2014",
      "slug": null,
      "grade": null,
      "sortTitle": "My America (2014)",
      "gradeValue": null,
      "releaseSequence": "2014-07-04tt3831696",
      "reviewDate": null,
      "viewingSequence": null,
      "watchlistDirectorNames": [],
      "watchlistPerformerNames": [],
      "watchlistWriterNames": [
        "Neil LaBute"
      ],
      "collectionNames": []
    },
    {
      "creditedAs": [
        "director",
        "writer"
      ],
      "imdbId": "tt3194590",
      "title": "Dirty Weekend",
      "year": "2015",
      "slug": null,
      "grade": null,
      "sortTitle": "Dirty Weekend (2015)",
      "gradeValue": null,
      "releaseSequence": "2015-04-19tt3194590",
      "reviewDate": null,
      "viewingSequence": null,
      "watchlistDirectorNames": [],
      "watchlistPerformerNames": [],
      "watchlistWriterNames": [
        "Neil LaBute"
      ],
      "collectionNames": []
    },
    {
      "creditedAs": [
        "writer"
      ],
      "imdbId": "tt2275743",
      "title": "Berlin, I Love You",
      "year": "2019",
      "slug": null,
      "grade": null,
      "sortTitle": "Berlin, I Love You (2019)",
      "gradeValue": null,
      "releaseSequence": "2019-02-08tt2275743",
      "reviewDate": null,
      "viewingSequence": null,
      "watchlistDirectorNames": [],
      "watchlistPerformerNames": [],
      "watchlistWriterNames": [
        "Neil LaBute"
      ],
      "collectionNames": []
    },
    {
      "creditedAs": [
        "director",
        "writer"
      ],
      "imdbId": "tt18224610",
      "title": "House of Darkness",
      "year": "2022",
      "slug": null,
      "grade": null,
      "sortTitle": "House of Darkness (2022)",
      "gradeValue": null,
      "releaseSequence": "2022-03-08tt18224610",
      "reviewDate": null,
      "viewingSequence": null,
      "watchlistDirectorNames": [],
      "watchlistPerformerNames": [],
      "watchlistWriterNames": [
        "Neil LaBute"
      ],
      "collectionNames": []
    },
    {
      "creditedAs": [
        "director",
        "writer"
      ],
      "imdbId": "tt15333788",
      "title": "Out of the Blue",
      "year": "2022",
      "slug": null,
      "grade": null,
      "sortTitle": "Out of the Blue (2022)",
      "gradeValue": null,
      "releaseSequence": "2022-08-22tt15333788",
      "reviewDate": null,
      "viewingSequence": null,
      "watchlistDirectorNames": [],
      "watchlistPerformerNames": [],
      "watchlistWriterNames": [
        "Neil LaBute"
      ],
      "collectionNames": []
    },
    {
      "creditedAs": [
        "director",
        "writer"
      ],
      "imdbId": "tt19848268",
      "title": "Fear the Night",
      "year": "2023",
      "slug": null,
      "grade": null,
      "sortTitle": "Fear the Night (2023)",
      "gradeValue": null,
      "releaseSequence": "2023-07-21tt19848268",
      "reviewDate": null,
      "viewingSequence": null,
      "watchlistDirectorNames": [],
      "watchlistPerformerNames": [],
      "watchlistWriterNames": [
        "Neil LaBute"
      ],
      "collectionNames": []
    },
    {
      "creditedAs": [
        "writer"
      ],
      "imdbId": "tt31631773",
      "title": "The Shape of Things",
      "year": "2023",
      "slug": null,
      "grade": null,
      "sortTitle": "Shape of Things (2023)",
      "gradeValue": null,
      "releaseSequence": "2023-08-08tt31631773",
      "reviewDate": null,
      "viewingSequence": null,
      "watchlistDirectorNames": [],
      "watchlistPerformerNames": [],
      "watchlistWriterNames": [
        "Neil LaBute"
      ],
      "collectionNames": []
    }
  ],
  "reviewCount": 1,
  "totalCount": 15,
  "creditedAs": [
    "writer",
    "director"
  ]
}