{
"viewingYear": "all",
"totalViewingCount": 1181,
"stats": [
{
"name": "Blu-ray",
"viewingCount": 232
},
{
"name": "Netflix",
"viewingCount": 193
},
{
"name": "TCM HD",
"viewingCount": 168
},
{
"name": "Watch TCM",
"viewingCount": 92
},
{
"name": "iTunes",
"viewingCount": 86
},
{
"name": "DVD",
"viewingCount": 62
},
{
"name": "Amazon",
"viewingCount": 56
},
{
"name": "Criterion Channel",
"viewingCount": 51
},
{
"name": "4k UHD Blu-ray",
"viewingCount": 44
},
{
"name": "Shudder",
"viewingCount": 27
}
]
}